{"411200": {"ADMINISTRATIVE_CODE": "411200", "PROVINCE": "\u6cb3\u5357\u7701", "CITY": "\u4e09\u95e8\u5ce1\u5e02", "COUNTY": "-", "STATISTICAL_YEAR": "1998", "MERCHISE_SALES_MONEY": "1130622.00000", "POPULATION_DENSITY": "1284.00000", "AMOUNT_WATER": "2636.00000", "BUS_PASSENGER_AMOUNT": "2064.00000", "ELECTRICITY_AMOUNT": "96558.00000", "HIGHWAY_PASSENGER_AMOUNT": "6952.00000", "HIGHWAY_FREIGHT": "4592.00000", "HOSPITAL_BEDS": "5907.00000", "NET_WORTH_BALANCE": "1088191.00000", "TOTAL_FIXED_INVEST": "367583.00000", "GDP_GROWTH_RATE": "14.60000", "GDP": "1448007.00000", "PASSENGER_VOLUME": "7198.00000", "PRIMARY_SCHOOL_TEACHERS": "11690", "PRIMARY_SCHOOL_STUDENTS": "26.03000", "PRIMARY_SCHOOL": "1289", "TOWN_EMPLOYMENT_PERSONNEL": "25.66000", "ACTUAL_RENTAL_CAR_NUMBER": "1096", "POPULATION": "214.60", "BUILT_AREA": "20.00000", "USE_FOREIGN_MONEY": "2418.00000", "ESTATE_INVEST_COMPLETE": "9680.00000", "MIDDLE_SCHOOL_TEACHERS": "7202", "MIDDLE_SCHOOL_STUDENTS": "10.68000", "MIDDLE_SCHOOL": "174", "DOMESTIC_VAT": "4.95450", "MILLION_LIBRARY": "22", "CURRENT_ASSETS_YEARS_BALANCE": "707323.00000", "LIQUIDGAS_TOTAL_AMOUNT_HOME": "1937.00000", "SOCIOLOGY_CONSUMER_QUOTA": "451420.00000", "FIRST_PEOPLE_PROPORTION": "1.10000", "FIRST_INDUSTRY_GDP": "15.50000", "THIRD_PEOPLE_PROPORTION": "41.50000", "THIRD_INDUSTRY_GDP": "33.50000", "TWO_PEOPLE_PROPORTION": "57.40000", "TWO_INDUSTRY_GDP": "50.90000", "WORKER_AVERAGE_WAGE": "0.54190", "NATURAL_POPULATION_GROWTH_RATE": "5.38000", "ADMINISTRATION_AREA": "10496.00000", "RAILWAY_TOTAL_FREIGHT": "5776.00000", "RAILWAY_PASSENGER_AMOUNT": "246.00000", "RAILWAY_FREIGHT": "1184.00000"}, "411500": {"ADMINISTRATIVE_CODE": "411500", "PROVINCE": "\u6cb3\u5357\u7701", "CITY": "\u4fe1\u9633\u5e02", "COUNTY": "-", "STATISTICAL_YEAR": "1998", "MERCHISE_SALES_MONEY": "656622.00000", "POPULATION_DENSITY": "375.00000", "AMOUNT_WATER": "5662.00000", "BUS_PASSENGER_AMOUNT": "498.00000", "ELECTRICITY_AMOUNT": "66353.00000", "HIGHWAY_PASSENGER_AMOUNT": "4787.00000", "HIGHWAY_FREIGHT": "2201.00000", "HOSPITAL_BEDS": "9735.00000", "NET_WORTH_BALANCE": "460667.00000", "TOTAL_FIXED_INVEST": "689586.00000", "GDP": "2288480.00000", "PASSENGER_VOLUME": "5100.00000", "PRIMARY_SCHOOL_TEACHERS": "36140", "PRIMARY_SCHOOL_STUDENTS": "91.41000", "PRIMARY_SCHOOL": "3169", "TOWN_EMPLOYMENT_PERSONNEL": "41.25000", "ACTUAL_RENTAL_CAR_NUMBER": "1779", "POPULATION": "766.96", "BUILT_AREA": "30.00000", "USE_FOREIGN_MONEY": "578.00000", "ESTATE_INVEST_COMPLETE": "7905.00000", "MIDDLE_SCHOOL_TEACHERS": "19213", "MIDDLE_SCHOOL_STUDENTS": "34.13000", "MIDDLE_SCHOOL": "439", "HIGH_SCHOOL_TEACHERS": "660", "ORDINA_HIGH_SCHOOL_STUDENTS": "4746", "HIGH_SCHOOL": "2", "DOMESTIC_VAT": "2.58840", "MILLION_LIBRARY": "6", "CURRENT_ASSETS_YEARS_BALANCE": "464746.00000", "LIQUIDGAS_TOTAL_AMOUNT_HOME": "2820.00000", "SOCIOLOGY_CONSUMER_QUOTA": "845300.00000", "FIRST_PEOPLE_PROPORTION": "3.30000", "FIRST_INDUSTRY_GDP": "39.00000", "THIRD_PEOPLE_PROPORTION": "62.90000", "THIRD_INDUSTRY_GDP": "29.60000", "TWO_PEOPLE_PROPORTION": "33.80000", "TWO_INDUSTRY_GDP": "31.40000", "WORKER_AVERAGE_WAGE": "0.47530", "NATURAL_POPULATION_GROWTH_RATE": "5.73000", "ADMINISTRATION_AREA": "18915.00000", "RAILWAY_TOTAL_FREIGHT": "2520.00000", "RAILWAY_PASSENGER_AMOUNT": "286.00000", "RAILWAY_FREIGHT": "209.00000"}, "411300": {"ADMINISTRATIVE_CODE": "411300", "PROVINCE": "\u6cb3\u5357\u7701", "CITY": "\u5357\u9633\u5e02", "COUNTY": "-", "STATISTICAL_YEAR": "1998", "MERCHISE_SALES_MONEY": "2174197.00000", "POPULATION_DENSITY": "815.00000", "AMOUNT_WATER": "8879.00000", "BUS_PASSENGER_AMOUNT": "1090.00000", "ELECTRICITY_AMOUNT": "192501.00000", "HIGHWAY_PASSENGER_AMOUNT": "5864.00000", "HIGHWAY_FREIGHT": "3487.00000", "HOSPITAL_BEDS": "14244.00000", "NET_WORTH_BALANCE": "1369437.00000", "TOTAL_FIXED_INVEST": "709597.00000", "GDP_GROWTH_RATE": "9.30000", "GDP": "2405946.00000", "PASSENGER_VOLUME": "6118.00000", "HOME_TOTAL_GAS_SUPPLY": "876.00000", "PRIMARY_SCHOOL_TEACHERS": "45384", "PRIMARY_SCHOOL_STUDENTS": "117.47000", "PRIMARY_SCHOOL": "4294", "TOWN_EMPLOYMENT_PERSONNEL": "76.28000", "ACTUAL_RENTAL_CAR_NUMBER": "1132", "POPULATION": "1041.95", "BUILT_AREA": "37.00000", "USE_FOREIGN_MONEY": "6901.00000", "ESTATE_INVEST_COMPLETE": "29460.00000", "MIDDLE_SCHOOL_TEACHERS": "33695", "MIDDLE_SCHOOL_STUDENTS": "62.03000", "MIDDLE_SCHOOL": "641", "HIGH_SCHOOL_TEACHERS": "545", "ORDINA_HIGH_SCHOOL_STUDENTS": "5255", "HIGH_SCHOOL": "2", "DOMESTIC_VAT": "10.31460", "MILLION_LIBRARY": "9", "CURRENT_ASSETS_YEARS_BALANCE": "1498445.00000", "LIQUIDGAS_TOTAL_AMOUNT_HOME": "4696.00000", "SOCIOLOGY_CONSUMER_QUOTA": "1470335.00000", "FIRST_PEOPLE_PROPORTION": "1.70000", "FIRST_INDUSTRY_GDP": "32.70000", "THIRD_PEOPLE_PROPORTION": "52.70000", "THIRD_INDUSTRY_GDP": "23.70000", "TWO_PEOPLE_PROPORTION": "45.60000", "TWO_INDUSTRY_GDP": "43.60000", "WORKER_AVERAGE_WAGE": "0.48830", "NATURAL_POPULATION_GROWTH_RATE": "6.56000", "ADMINISTRATION_AREA": "26400.00000", "RAILWAY_TOTAL_FREIGHT": "3789.00000", "RAILWAY_PASSENGER_AMOUNT": "177.00000", "RAILWAY_FREIGHT": "169.00000"}, "411600": {"ADMINISTRATIVE_CODE": "411600", "PROVINCE": "\u6cb3\u5357\u7701", "CITY": "\u5468\u53e3\u5e02", "COUNTY": "-", "STATISTICAL_YEAR": "1998", "GDP_GROWTH_RATE": "7.90000", "PRIMARY_SCHOOL_TEACHERS": "1605", "PRIMARY_SCHOOL_STUDENTS": "3.23000", "PRIMARY_SCHOOL": "67", "MIDDLE_SCHOOL_TEACHERS": "1273", "MIDDLE_SCHOOL_STUDENTS": "1.80000", "MIDDLE_SCHOOL": "18", "SOCIOLOGY_CONSUMER_QUOTA": "134073.00000", "FIRST_INDUSTRY_GDP": "5.90000", "THIRD_INDUSTRY_GDP": "50.80000", "TWO_INDUSTRY_GDP": "43.30000"}, "411400": {"ADMINISTRATIVE_CODE": "411400", "PROVINCE": "\u6cb3\u5357\u7701", "CITY": "\u5546\u4e18\u5e02", "COUNTY": "-", "STATISTICAL_YEAR": "1998", "MERCHISE_SALES_MONEY": "741827.00000", "POPULATION_DENSITY": "867.00000", "AMOUNT_WATER": "5653.00000", "BUS_PASSENGER_AMOUNT": "1849.00000", "ELECTRICITY_AMOUNT": "55197.00000", "HIGHWAY_PASSENGER_AMOUNT": "3202.00000", "HIGHWAY_FREIGHT": "2209.00000", "HOSPITAL_BEDS": "12593.00000", "NET_WORTH_BALANCE": "508708.00000", "TOTAL_FIXED_INVEST": "380839.00000", "GDP": "4658731.00000", "PASSENGER_VOLUME": "3435.00000", "TOWN_EMPLOYMENT_PERSONNEL": "40.98000", "ACTUAL_RENTAL_CAR_NUMBER": "1120", "POPULATION": "795.50", "BUILT_AREA": "36.00000", "USE_FOREIGN_MONEY": "1498.00000", "ESTATE_INVEST_COMPLETE": "10656.00000", "DOMESTIC_VAT": "2.83380", "MILLION_LIBRARY": "6", "CURRENT_ASSETS_YEARS_BALANCE": "553072.00000", "LIQUIDGAS_TOTAL_AMOUNT_HOME": "1200.00000", "FIRST_PEOPLE_PROPORTION": "1.60000", "THIRD_PEOPLE_PROPORTION": "66.90000", "TWO_PEOPLE_PROPORTION": "31.60000", "WORKER_AVERAGE_WAGE": "0.44150", "NATURAL_POPULATION_GROWTH_RATE": "3.75000", "ADMINISTRATION_AREA": "10704.00000", "RAILWAY_TOTAL_FREIGHT": "2341.00000", "RAILWAY_PASSENGER_AMOUNT": "233.00000", "RAILWAY_FREIGHT": "101.00000"}, "410500": {"ADMINISTRATIVE_CODE": "410500", "PROVINCE": "\u6cb3\u5357\u7701", "CITY": "\u5b89\u9633\u5e02", "COUNTY": "-", "STATISTICAL_YEAR": "1998", "MERCHISE_SALES_MONEY": "1520898.00000", "POPULATION_DENSITY": "2908.00000", "AMOUNT_WATER": "20537.00000", "BUS_PASSENGER_AMOUNT": "1932.00000", "ELECTRICITY_AMOUNT": "293808.00000", "HIGHWAY_PASSENGER_AMOUNT": "3897.00000", "HIGHWAY_FREIGHT": "2785.00000", "HOSPITAL_BEDS": "8281.00000", "NET_WORTH_BALANCE": "1155606.00000", "TOTAL_FIXED_INVEST": "314298.00000", "GDP_GROWTH_RATE": "3.70000", "GDP": "2212881.00000", "PASSENGER_VOLUME": "4118.00000", "HOME_TOTAL_GAS_SUPPLY": "3514.00000", "PRIMARY_SCHOOL_TEACHERS": "23247", "PRIMARY_SCHOOL_STUDENTS": "66.93000", "PRIMARY_SCHOOL": "2707", "TOWN_EMPLOYMENT_PERSONNEL": "41.88000", "ACTUAL_RENTAL_CAR_NUMBER": "2100", "POPULATION": "508.73", "BUILT_AREA": "44.00000", "USE_FOREIGN_MONEY": "196.00000", "ESTATE_INVEST_COMPLETE": "13664.00000", "MIDDLE_SCHOOL_TEACHERS": "14968", "MIDDLE_SCHOOL_STUDENTS": "28.52000", "MIDDLE_SCHOOL": "359", "HIGH_SCHOOL_TEACHERS": "489", "ORDINA_HIGH_SCHOOL_STUDENTS": "4140", "HIGH_SCHOOL": "2", "DOMESTIC_VAT": "7.33470", "MILLION_LIBRARY": "11", "CURRENT_ASSETS_YEARS_BALANCE": "1345972.00000", "LIQUIDGAS_TOTAL_AMOUNT_HOME": "6146.00000", "SOCIOLOGY_CONSUMER_QUOTA": "693542.00000", "FIRST_PEOPLE_PROPORTION": "0.70000", "FIRST_INDUSTRY_GDP": "23.00000", "THIRD_PEOPLE_PROPORTION": "45.70000", "THIRD_INDUSTRY_GDP": "31.40000", "TWO_PEOPLE_PROPORTION": "53.60000", "TWO_INDUSTRY_GDP": "45.60000", "WORKER_AVERAGE_WAGE": "0.59650", "NATURAL_POPULATION_GROWTH_RATE": "5.63000", "ADMINISTRATION_AREA": "7413.00000", "RAILWAY_TOTAL_FREIGHT": "3161.00000", "RAILWAY_PASSENGER_AMOUNT": "221.00000", "RAILWAY_FREIGHT": "376.00000"}, "410400": {"ADMINISTRATIVE_CODE": "410400", "PROVINCE": "\u6cb3\u5357\u7701", "CITY": "\u5e73\u9876\u5c71\u5e02", "COUNTY": "-", "STATISTICAL_YEAR": "1998", "MERCHISE_SALES_MONEY": "1381160.00000", "POPULATION_DENSITY": "1846.00000", "AMOUNT_WATER": "9598.00000", "BUS_PASSENGER_AMOUNT": "4035.00000", "ELECTRICITY_AMOUNT": "296673.00000", "HIGHWAY_PASSENGER_AMOUNT": "4768.00000", "HIGHWAY_FREIGHT": "3100.00000", "HOSPITAL_BEDS": "11082.00000", "NET_WORTH_BALANCE": "1264130.00000", "TOTAL_FIXED_INVEST": "418755.00000", "GDP_GROWTH_RATE": "8.60000", "GDP": "2390078.00000", "PASSENGER_VOLUME": "4857.00000", "HOME_TOTAL_GAS_SUPPLY": "4441.00000", "PRIMARY_SCHOOL_TEACHERS": "23470", "PRIMARY_SCHOOL_STUDENTS": "60.15000", "PRIMARY_SCHOOL": "2387", "TOWN_EMPLOYMENT_PERSONNEL": "55.79000", "ACTUAL_RENTAL_CAR_NUMBER": "2268", "POPULATION": "475.75", "BUILT_AREA": "42.00000", "USE_FOREIGN_MONEY": "714.00000", "ESTATE_INVEST_COMPLETE": "26414.00000", "MIDDLE_SCHOOL_TEACHERS": "13606", "MIDDLE_SCHOOL_STUDENTS": "23.17000", "MIDDLE_SCHOOL": "306", "HIGH_SCHOOL_TEACHERS": "455", "ORDINA_HIGH_SCHOOL_STUDENTS": "3435", "HIGH_SCHOOL": "2", "DOMESTIC_VAT": "8.36970", "MILLION_LIBRARY": "11", "CURRENT_ASSETS_YEARS_BALANCE": "1321038.00000", "LIQUIDGAS_TOTAL_AMOUNT_HOME": "720.00000", "SOCIOLOGY_CONSUMER_QUOTA": "707886.00000", "FIRST_PEOPLE_PROPORTION": "0.60000", "FIRST_INDUSTRY_GDP": "16.90000", "THIRD_PEOPLE_PROPORTION": "39.20000", "THIRD_INDUSTRY_GDP": "30.90000", "TWO_PEOPLE_PROPORTION": "60.20000", "TWO_INDUSTRY_GDP": "52.20000", "WORKER_AVERAGE_WAGE": "0.64720", "NATURAL_POPULATION_GROWTH_RATE": "5.10000", "ADMINISTRATION_AREA": "7882.00000", "RAILWAY_TOTAL_FREIGHT": "5558.00000", "RAILWAY_PASSENGER_AMOUNT": "89.00000", "RAILWAY_FREIGHT": "2458.00000"}, "410200": {"ADMINISTRATIVE_CODE": "410200", "PROVINCE": "\u6cb3\u5357\u7701", "CITY": "\u5f00\u5c01\u5e02", "COUNTY": "-", "STATISTICAL_YEAR": "1998", "MERCHISE_SALES_MONEY": "802785.00000", "POPULATION_DENSITY": "2066.00000", "AMOUNT_WATER": "11053.00000", "BUS_PASSENGER_AMOUNT": "2386.00000", "ELECTRICITY_AMOUNT": "112423.00000", "HIGHWAY_PASSENGER_AMOUNT": "2908.00000", "HIGHWAY_FREIGHT": "1919.00000", "HOSPITAL_BEDS": "11184.00000", "NET_WORTH_BALANCE": "462132.00000", "TOTAL_FIXED_INVEST": "209116.00000", "GDP_GROWTH_RATE": "9.00000", "GDP": "1885971.00000", "PASSENGER_VOLUME": "3039.00000", "HOME_TOTAL_GAS_SUPPLY": "791.00000", "PRIMARY_SCHOOL_TEACHERS": "19286", "PRIMARY_SCHOOL_STUDENTS": "62.67000", "PRIMARY_SCHOOL": "1895", "TOWN_EMPLOYMENT_PERSONNEL": "39.34000", "ACTUAL_RENTAL_CAR_NUMBER": "2000", "POPULATION": "460.71", "BUILT_AREA": "50.00000", "USE_FOREIGN_MONEY": "374.00000", "ESTATE_INVEST_COMPLETE": "23837.00000", "MIDDLE_SCHOOL_TEACHERS": "14205", "MIDDLE_SCHOOL_STUDENTS": "28.64000", "MIDDLE_SCHOOL": "313", "HIGH_SCHOOL_TEACHERS": "2229", "ORDINA_HIGH_SCHOOL_STUDENTS": "12527", "HIGH_SCHOOL": "5", "DOMESTIC_VAT": "2.40490", "MILLION_LIBRARY": "15", "CURRENT_ASSETS_YEARS_BALANCE": "676377.00000", "LIQUIDGAS_TOTAL_AMOUNT_HOME": "2220.00000", "SOCIOLOGY_CONSUMER_QUOTA": "704734.00000", "FIRST_PEOPLE_PROPORTION": "1.40000", "FIRST_INDUSTRY_GDP": "34.80000", "THIRD_PEOPLE_PROPORTION": "53.80000", "THIRD_INDUSTRY_GDP": "29.80000", "TWO_PEOPLE_PROPORTION": "44.80000", "TWO_INDUSTRY_GDP": "35.40000", "WORKER_AVERAGE_WAGE": "0.48000", "NATURAL_POPULATION_GROWTH_RATE": "4.85000", "ADMINISTRATION_AREA": "6444.00000", "RAILWAY_TOTAL_FREIGHT": "2020.00000", "RAILWAY_PASSENGER_AMOUNT": "131.00000", "RAILWAY_FREIGHT": "101.00000"}, "410700": {"ADMINISTRATIVE_CODE": "410700", "PROVINCE": "\u6cb3\u5357\u7701", "CITY": "\u65b0\u4e61\u5e02", "COUNTY": "-", "STATISTICAL_YEAR": "1998", "MERCHISE_SALES_MONEY": "1692359.00000", "POPULATION_DENSITY": "3857.00000", "AMOUNT_WATER": "12730.00000", "BUS_PASSENGER_AMOUNT": "2729.00000", "ELECTRICITY_AMOUNT": "177032.00000", "HIGHWAY_PASSENGER_AMOUNT": "2376.00000", "HIGHWAY_FREIGHT": "2699.00000", "HOSPITAL_BEDS": "13748.00000", "NET_WORTH_BALANCE": "1351007.00000", "TOTAL_FIXED_INVEST": "359770.00000", "GDP_GROWTH_RATE": "6.20000", "GDP": "2560521.00000", "PASSENGER_VOLUME": "2634.00000", "HOME_TOTAL_GAS_SUPPLY": "853.00000", "PRIMARY_SCHOOL_TEACHERS": "21428", "PRIMARY_SCHOOL_STUDENTS": "73.46000", "PRIMARY_SCHOOL": "2743", "TOWN_EMPLOYMENT_PERSONNEL": "51.70000", "ACTUAL_RENTAL_CAR_NUMBER": "2800", "POPULATION": "529.21", "BUILT_AREA": "53.00000", "USE_FOREIGN_MONEY": "4616.00000", "ESTATE_INVEST_COMPLETE": "17167.00000", "MIDDLE_SCHOOL_TEACHERS": "17176", "MIDDLE_SCHOOL_STUDENTS": "31.04000", "MIDDLE_SCHOOL": "452", "HIGH_SCHOOL_TEACHERS": "1923", "ORDINA_HIGH_SCHOOL_STUDENTS": "15989", "HIGH_SCHOOL": "6", "DOMESTIC_VAT": "7.10280", "MILLION_LIBRARY": "15", "CURRENT_ASSETS_YEARS_BALANCE": "1224350.00000", "LIQUIDGAS_TOTAL_AMOUNT_HOME": "4027.00000", "SOCIOLOGY_CONSUMER_QUOTA": "913851.00000", "FIRST_PEOPLE_PROPORTION": "0.80000", "FIRST_INDUSTRY_GDP": "26.60000", "THIRD_PEOPLE_PROPORTION": "49.30000", "THIRD_INDUSTRY_GDP": "33.00000", "TWO_PEOPLE_PROPORTION": "49.90000", "TWO_INDUSTRY_GDP": "40.40000", "WORKER_AVERAGE_WAGE": "0.52940", "NATURAL_POPULATION_GROWTH_RATE": "4.81000", "ADMINISTRATION_AREA": "8169.00000", "RAILWAY_TOTAL_FREIGHT": "2954.00000", "RAILWAY_PASSENGER_AMOUNT": "258.00000", "RAILWAY_FREIGHT": "255.00000"}, "410300": {"ADMINISTRATIVE_CODE": "410300", "PROVINCE": "\u6cb3\u5357\u7701", "CITY": "\u6d1b\u9633\u5e02", "COUNTY": "-", "STATISTICAL_YEAR": "1998", "MERCHISE_SALES_MONEY": "2712086.00000", "POPULATION_DENSITY": "2593.00000", "AMOUNT_WATER": "21961.00000", "BUS_PASSENGER_AMOUNT": "8499.00000", "ELECTRICITY_AMOUNT": "324869.00000", "HIGHWAY_PASSENGER_AMOUNT": "8808.00000", "HIGHWAY_FREIGHT": "4410.00000", "HOSPITAL_BEDS": "16183.00000", "NET_WORTH_BALANCE": "1995672.00000", "TOTAL_FIXED_INVEST": "961107.00000", "GDP_GROWTH_RATE": "11.50000", "GDP": "3648262.00000", "PASSENGER_VOLUME": "9179.00000", "HOME_TOTAL_GAS_SUPPLY": "2657.00000", "PRIMARY_SCHOOL_TEACHERS": "26248", "PRIMARY_SCHOOL_STUDENTS": "73.65000", "PRIMARY_SCHOOL": "2912", "TOWN_EMPLOYMENT_PERSONNEL": "64.61000", "ACTUAL_RENTAL_CAR_NUMBER": "3930", "POPULATION": "611.71", "BUILT_AREA": "92.00000", "USE_FOREIGN_MONEY": "9336.00000", "ESTATE_INVEST_COMPLETE": "65733.00000", "MIDDLE_SCHOOL_TEACHERS": "21120", "MIDDLE_SCHOOL_STUDENTS": "32.99000", "MIDDLE_SCHOOL": "502", "HIGH_SCHOOL_TEACHERS": "1615", "ORDINA_HIGH_SCHOOL_STUDENTS": "14840", "HIGH_SCHOOL": "6", "DOMESTIC_VAT": "10.94100", "MILLION_LIBRARY": "15", "CURRENT_ASSETS_YEARS_BALANCE": "2499650.00000", "LIQUIDGAS_TOTAL_AMOUNT_HOME": "20929.00000", "SOCIOLOGY_CONSUMER_QUOTA": "1462900.00000", "FIRST_PEOPLE_PROPORTION": "0.60000", "FIRST_INDUSTRY_GDP": "11.00000", "THIRD_PEOPLE_PROPORTION": "44.50000", "THIRD_INDUSTRY_GDP": "34.90000", "TWO_PEOPLE_PROPORTION": "54.90000", "TWO_INDUSTRY_GDP": "54.10000", "WORKER_AVERAGE_WAGE": "0.65060", "NATURAL_POPULATION_GROWTH_RATE": "4.96000", "ADMINISTRATION_AREA": "15209.00000", "RAILWAY_TOTAL_FREIGHT": "5046.00000", "RAILWAY_PASSENGER_AMOUNT": "369.00000", "RAILWAY_FREIGHT": "636.00000"}, "411100": {"ADMINISTRATIVE_CODE": "411100", "PROVINCE": "\u6cb3\u5357\u7701", "CITY": "\u6f2f\u6cb3\u5e02", "COUNTY": "-", "STATISTICAL_YEAR": "1998", "MERCHISE_SALES_MONEY": "1311877.00000", "POPULATION_DENSITY": "4269.00000", "AMOUNT_WATER": "7614.00000", "BUS_PASSENGER_AMOUNT": "2139.00000", "ELECTRICITY_AMOUNT": "44548.00000", "HIGHWAY_PASSENGER_AMOUNT": "2104.00000", "HIGHWAY_FREIGHT": "1235.00000", "HOSPITAL_BEDS": "4500.00000", "NET_WORTH_BALANCE": "473553.00000", "TOTAL_FIXED_INVEST": "439935.00000", "GDP_GROWTH_RATE": "11.50000", "GDP": "1366115.00000", "PASSENGER_VOLUME": "2271.00000", "HOME_TOTAL_GAS_SUPPLY": "54.00000", "PRIMARY_SCHOOL_TEACHERS": "11462", "PRIMARY_SCHOOL_STUDENTS": "29.53000", "PRIMARY_SCHOOL": "987", "TOWN_EMPLOYMENT_PERSONNEL": "20.73000", "ACTUAL_RENTAL_CAR_NUMBER": "1078", "POPULATION": "250.24", "BUILT_AREA": "24.00000", "USE_FOREIGN_MONEY": "4510.00000", "ESTATE_INVEST_COMPLETE": "18119.00000", "MIDDLE_SCHOOL_TEACHERS": "7212", "MIDDLE_SCHOOL_STUDENTS": "14.57000", "MIDDLE_SCHOOL": "131", "DOMESTIC_VAT": "2.91600", "MILLION_LIBRARY": "10", "CURRENT_ASSETS_YEARS_BALANCE": "562057.00000", "LIQUIDGAS_TOTAL_AMOUNT_HOME": "2477.00000", "SOCIOLOGY_CONSUMER_QUOTA": "488600.00000", "FIRST_PEOPLE_PROPORTION": "0.80000", "FIRST_INDUSTRY_GDP": "26.40000", "THIRD_PEOPLE_PROPORTION": "50.20000", "THIRD_INDUSTRY_GDP": "23.10000", "TWO_PEOPLE_PROPORTION": "49.00000", "TWO_INDUSTRY_GDP": "50.50000", "WORKER_AVERAGE_WAGE": "0.45740", "NATURAL_POPULATION_GROWTH_RATE": "4.04000", "ADMINISTRATION_AREA": "2617.00000", "RAILWAY_TOTAL_FREIGHT": "1414.00000", "RAILWAY_PASSENGER_AMOUNT": "167.00000", "RAILWAY_FREIGHT": "171.00000"}, "410900": {"ADMINISTRATIVE_CODE": "410900", "PROVINCE": "\u6cb3\u5357\u7701", "CITY": "\u6fee\u9633\u5e02", "COUNTY": "-", "STATISTICAL_YEAR": "1998", "MERCHISE_SALES_MONEY": "1159602.00000", "POPULATION_DENSITY": "1823.00000", "AMOUNT_WATER": "3967.00000", "BUS_PASSENGER_AMOUNT": "862.00000", "ELECTRICITY_AMOUNT": "211859.00000", "HIGHWAY_PASSENGER_AMOUNT": "2634.00000", "HIGHWAY_FREIGHT": "1165.00000", "HOSPITAL_BEDS": "6688.00000", "NET_WORTH_BALANCE": "1645573.00000", "TOTAL_FIXED_INVEST": "445699.00000", "GDP_GROWTH_RATE": "6.70000", "GDP": "1705816.00000", "PASSENGER_VOLUME": "2648.00000", "HOME_TOTAL_GAS_SUPPLY": "1093.00000", "PRIMARY_SCHOOL_TEACHERS": "15223", "PRIMARY_SCHOOL_STUDENTS": "48.45000", "PRIMARY_SCHOOL": "1972", "TOWN_EMPLOYMENT_PERSONNEL": "34.75000", "ACTUAL_RENTAL_CAR_NUMBER": "2400", "POPULATION": "347.39", "BUILT_AREA": "25.00000", "USE_FOREIGN_MONEY": "1857.00000", "ESTATE_INVEST_COMPLETE": "13713.00000", "MIDDLE_SCHOOL_TEACHERS": "10104", "MIDDLE_SCHOOL_STUDENTS": "20.71000", "MIDDLE_SCHOOL": "234", "ORDINA_HIGH_SCHOOL_STUDENTS": "770", "DOMESTIC_VAT": "5.09170", "MILLION_LIBRARY": "14", "CURRENT_ASSETS_YEARS_BALANCE": "906435.00000", "LIQUIDGAS_TOTAL_AMOUNT_HOME": "14117.00000", "SOCIOLOGY_CONSUMER_QUOTA": "450593.00000", "FIRST_PEOPLE_PROPORTION": "0.80000", "FIRST_INDUSTRY_GDP": "23.60000", "THIRD_PEOPLE_PROPORTION": "41.50000", "THIRD_INDUSTRY_GDP": "24.60000", "TWO_PEOPLE_PROPORTION": "57.70000", "TWO_INDUSTRY_GDP": "51.80000", "WORKER_AVERAGE_WAGE": "0.68120", "NATURAL_POPULATION_GROWTH_RATE": "4.63000", "ADMINISTRATION_AREA": "4266.00000", "RAILWAY_TOTAL_FREIGHT": "1311.00000", "RAILWAY_PASSENGER_AMOUNT": "14.00000", "RAILWAY_FREIGHT": "146.00000"}, "410800": {"ADMINISTRATIVE_CODE": "410800", "PROVINCE": "\u6cb3\u5357\u7701", "CITY": "\u7126\u4f5c\u5e02", "COUNTY": "-", "STATISTICAL_YEAR": "1998", "MERCHISE_SALES_MONEY": "2257251.00000", "POPULATION_DENSITY": "1887.00000", "AMOUNT_WATER": "11747.00000", "BUS_PASSENGER_AMOUNT": "3512.00000", "ELECTRICITY_AMOUNT": "259756.00000", "HIGHWAY_PASSENGER_AMOUNT": "2309.00000", "HIGHWAY_FREIGHT": "3773.00000", "HOSPITAL_BEDS": "8932.00000", "NET_WORTH_BALANCE": "1228756.00000", "TOTAL_FIXED_INVEST": "392484.00000", "GDP_GROWTH_RATE": "4.30000", "GDP": "2508236.00000", "PASSENGER_VOLUME": "2620.00000", "HOME_TOTAL_GAS_SUPPLY": "1829.00000", "PRIMARY_SCHOOL_TEACHERS": "12958", "PRIMARY_SCHOOL_STUDENTS": "37.36000", "PRIMARY_SCHOOL": "1162", "TOWN_EMPLOYMENT_PERSONNEL": "39.90000", "ACTUAL_RENTAL_CAR_NUMBER": "1322", "POPULATION": "320.32", "BUILT_AREA": "46.00000", "USE_FOREIGN_MONEY": "4686.00000", "ESTATE_INVEST_COMPLETE": "13996.00000", "MIDDLE_SCHOOL_TEACHERS": "11345", "MIDDLE_SCHOOL_STUDENTS": "18.59000", "MIDDLE_SCHOOL": "258", "HIGH_SCHOOL_TEACHERS": "794", "ORDINA_HIGH_SCHOOL_STUDENTS": "6856", "HIGH_SCHOOL": "2", "DOMESTIC_VAT": "8.31070", "MILLION_LIBRARY": "14", "CURRENT_ASSETS_YEARS_BALANCE": "1233191.00000", "LIQUIDGAS_TOTAL_AMOUNT_HOME": "5431.00000", "SOCIOLOGY_CONSUMER_QUOTA": "637241.00000", "FIRST_PEOPLE_PROPORTION": "1.30000", "FIRST_INDUSTRY_GDP": "16.30000", "THIRD_PEOPLE_PROPORTION": "39.50000", "THIRD_INDUSTRY_GDP": "23.70000", "TWO_PEOPLE_PROPORTION": "59.20000", "TWO_INDUSTRY_GDP": "60.00000", "WORKER_AVERAGE_WAGE": "0.51170", "NATURAL_POPULATION_GROWTH_RATE": "5.27000", "ADMINISTRATION_AREA": "4071.00000", "RAILWAY_TOTAL_FREIGHT": "5420.00000", "RAILWAY_PASSENGER_AMOUNT": "311.00000", "RAILWAY_FREIGHT": "1647.00000"}, "411000": {"ADMINISTRATIVE_CODE": "411000", "PROVINCE": "\u6cb3\u5357\u7701", "CITY": "\u8bb8\u660c\u5e02", "COUNTY": "-", "STATISTICAL_YEAR": "1998", "MERCHISE_SALES_MONEY": "1520080.00000", "POPULATION_DENSITY": "3610.00000", "AMOUNT_WATER": "3706.00000", "BUS_PASSENGER_AMOUNT": "1110.00000", "ELECTRICITY_AMOUNT": "58566.00000", "HIGHWAY_PASSENGER_AMOUNT": "2343.00000", "HIGHWAY_FREIGHT": "2546.00000", "HOSPITAL_BEDS": "7303.00000", "NET_WORTH_BALANCE": "574660.00000", "TOTAL_FIXED_INVEST": "325348.00000", "GDP_GROWTH_RATE": "11.80000", "GDP": "2429190.00000", "PASSENGER_VOLUME": "2441.00000", "PRIMARY_SCHOOL_TEACHERS": "18914", "PRIMARY_SCHOOL_STUDENTS": "54.88000", "PRIMARY_SCHOOL": "2082", "TOWN_EMPLOYMENT_PERSONNEL": "28.48000", "ACTUAL_RENTAL_CAR_NUMBER": "1500", "POPULATION": "433.44", "BUILT_AREA": "23.00000", "USE_FOREIGN_MONEY": "687.00000", "ESTATE_INVEST_COMPLETE": "9973.00000", "MIDDLE_SCHOOL_TEACHERS": "12741", "MIDDLE_SCHOOL_STUDENTS": "22.81000", "MIDDLE_SCHOOL": "300", "HIGH_SCHOOL_TEACHERS": "225", "ORDINA_HIGH_SCHOOL_STUDENTS": "2269", "HIGH_SCHOOL": "1", "DOMESTIC_VAT": "4.55070", "MILLION_LIBRARY": "8", "CURRENT_ASSETS_YEARS_BALANCE": "783339.00000", "LIQUIDGAS_TOTAL_AMOUNT_HOME": "2304.00000", "SOCIOLOGY_CONSUMER_QUOTA": "693286.00000", "FIRST_PEOPLE_PROPORTION": "1.40000", "FIRST_INDUSTRY_GDP": "23.10000", "THIRD_PEOPLE_PROPORTION": "57.30000", "THIRD_INDUSTRY_GDP": "26.10000", "TWO_PEOPLE_PROPORTION": "41.30000", "TWO_INDUSTRY_GDP": "50.90000", "WORKER_AVERAGE_WAGE": "0.52520", "NATURAL_POPULATION_GROWTH_RATE": "5.70000", "ADMINISTRATION_AREA": "4994.00000", "RAILWAY_TOTAL_FREIGHT": "2762.00000", "RAILWAY_PASSENGER_AMOUNT": "98.00000", "RAILWAY_FREIGHT": "216.00000"}, "410100": {"ADMINISTRATIVE_CODE": "410100", "PROVINCE": "\u6cb3\u5357\u7701", "CITY": "\u90d1\u5dde\u5e02", "COUNTY": "-", "STATISTICAL_YEAR": "1998", "MERCHISE_SALES_MONEY": "5837100.00000", "POPULATION_DENSITY": "2019.00000", "AMOUNT_WATER": "33890.00000", "BUS_PASSENGER_AMOUNT": "19510.00000", "ELECTRICITY_AMOUNT": "658039.00000", "HIGHWAY_PASSENGER_AMOUNT": "7321.00000", "HIGHWAY_FREIGHT": "5342.00000", "HOSPITAL_BEDS": "21523.00000", "NET_WORTH_BALANCE": "3823100.00000", "TOTAL_FIXED_INVEST": "1292537.00000", "GDP_GROWTH_RATE": "10.00000", "GDP": "6203185.00000", "PASSENGER_VOLUME": "8591.00000", "HOME_TOTAL_GAS_SUPPLY": "4950.00000", "PRIMARY_SCHOOL_TEACHERS": "26984", "PRIMARY_SCHOOL_STUDENTS": "83.85000", "PRIMARY_SCHOOL": "1975", "TOWN_EMPLOYMENT_PERSONNEL": "90.76000", "ACTUAL_RENTAL_CAR_NUMBER": "10737", "POPULATION": "606.02", "BUILT_AREA": "116.00000", "USE_FOREIGN_MONEY": "23803.00000", "ESTATE_INVEST_COMPLETE": "301733.00000", "MIDDLE_SCHOOL_TEACHERS": "18772", "MIDDLE_SCHOOL_STUDENTS": "32.61000", "MIDDLE_SCHOOL": "433", "HIGH_SCHOOL_TEACHERS": "7411", "ORDINA_HIGH_SCHOOL_STUDENTS": "70585", "HIGH_SCHOOL": "20", "DOMESTIC_VAT": "11.42120", "MILLION_LIBRARY": "52", "CURRENT_ASSETS_YEARS_BALANCE": "3764100.00000", "LIQUIDGAS_TOTAL_AMOUNT_HOME": "16089.00000", "SOCIOLOGY_CONSUMER_QUOTA": "2856600.00000", "FIRST_PEOPLE_PROPORTION": "0.60000", "FIRST_INDUSTRY_GDP": "6.30000", "THIRD_PEOPLE_PROPORTION": "50.80000", "THIRD_INDUSTRY_GDP": "40.00000", "TWO_PEOPLE_PROPORTION": "48.60000", "TWO_INDUSTRY_GDP": "53.80000", "WORKER_AVERAGE_WAGE": "0.77440", "NATURAL_POPULATION_GROWTH_RATE": "4.99000", "ADMINISTRATION_AREA": "7446.00000", "RAILWAY_TOTAL_FREIGHT": "6838.00000", "RAILWAY_PASSENGER_AMOUNT": "1198.00000", "RAILWAY_FREIGHT": "1495.00000"}, "411700": {"ADMINISTRATIVE_CODE": "411700", "PROVINCE": "\u6cb3\u5357\u7701", "CITY": "\u9a7b\u9a6c\u5e97\u5e02", "COUNTY": "-", "STATISTICAL_YEAR": "1998", "GDP_GROWTH_RATE": "10.40000", "PRIMARY_SCHOOL_TEACHERS": "1604", "PRIMARY_SCHOOL_STUDENTS": "2.79000", "PRIMARY_SCHOOL": "50", "MIDDLE_SCHOOL_TEACHERS": "1322", "MIDDLE_SCHOOL_STUDENTS": "1.63000", "MIDDLE_SCHOOL": "24", "SOCIOLOGY_CONSUMER_QUOTA": "159000.00000", "FIRST_INDUSTRY_GDP": "4.30000", "THIRD_INDUSTRY_GDP": "40.50000", "TWO_INDUSTRY_GDP": "55.20000"}, "410600": {"ADMINISTRATIVE_CODE": "410600", "PROVINCE": "\u6cb3\u5357\u7701", "CITY": "\u9e64\u58c1\u5e02", "COUNTY": "-", "STATISTICAL_YEAR": "1998", "MERCHISE_SALES_MONEY": "522522.00000", "POPULATION_DENSITY": "782.00000", "AMOUNT_WATER": "5273.00000", "BUS_PASSENGER_AMOUNT": "2215.00000", "ELECTRICITY_AMOUNT": "81906.00000", "HIGHWAY_PASSENGER_AMOUNT": "825.00000", "HIGHWAY_FREIGHT": "1374.00000", "HOSPITAL_BEDS": "3516.00000", "NET_WORTH_BALANCE": "431054.00000", "TOTAL_FIXED_INVEST": "150912.00000", "GDP_GROWTH_RATE": "6.90000", "GDP": "732335.00000", "PASSENGER_VOLUME": "848.00000", "HOME_TOTAL_GAS_SUPPLY": "403.00000", "PRIMARY_SCHOOL_TEACHERS": "6189", "PRIMARY_SCHOOL_STUDENTS": "18.40000", "PRIMARY_SCHOOL": "422", "TOWN_EMPLOYMENT_PERSONNEL": "18.11000", "ACTUAL_RENTAL_CAR_NUMBER": "600", "POPULATION": "134.86", "BUILT_AREA": "32.00000", "USE_FOREIGN_MONEY": "347.00000", "ESTATE_INVEST_COMPLETE": "1184.00000", "MIDDLE_SCHOOL_TEACHERS": "3982", "MIDDLE_SCHOOL_STUDENTS": "7.07000", "MIDDLE_SCHOOL": "83", "DOMESTIC_VAT": "2.24830", "MILLION_LIBRARY": "20", "CURRENT_ASSETS_YEARS_BALANCE": "519710.00000", "LIQUIDGAS_TOTAL_AMOUNT_HOME": "2600.00000", "SOCIOLOGY_CONSUMER_QUOTA": "181869.00000", "FIRST_PEOPLE_PROPORTION": "1.60000", "FIRST_INDUSTRY_GDP": "24.40000", "THIRD_PEOPLE_PROPORTION": "35.50000", "THIRD_INDUSTRY_GDP": "27.70000", "TWO_PEOPLE_PROPORTION": "62.90000", "TWO_INDUSTRY_GDP": "47.90000", "WORKER_AVERAGE_WAGE": "0.51990", "NATURAL_POPULATION_GROWTH_RATE": "4.99000", "ADMINISTRATION_AREA": "2137.00000", "RAILWAY_TOTAL_FREIGHT": "1705.00000", "RAILWAY_PASSENGER_AMOUNT": "23.00000", "RAILWAY_FREIGHT": "331.00000"}}