{"630200": {"ADMINISTRATIVE_CODE": "630200", "PROVINCE": "\u9752\u6d77\u7701", "CITY": "\u6d77\u4e1c\u5e02", "COUNTY": "-", "STATISTICAL_YEAR": "2008"}, "630100": {"ADMINISTRATIVE_CODE": "630100", "PROVINCE": "\u9752\u6d77\u7701", "CITY": "\u897f\u5b81\u5e02", "COUNTY": "-", "STATISTICAL_YEAR": "2008", "THIRD_TRANSPORT_WAREHOU_POSTAL": "22100", "MERCHISE_SALES_MONEY": "4708167.00000", "POPULATION_DENSITY": "284.73000", "PER_CAPITA_GDP": "19494.00000", "PER_CAPITA_ROAD_AREA": "7.05000", "PARK_GREEN_SPACE_AREA": "786.00000", "THIRD_LIVE_EAT": "2400", "GAS_AMOUNT": "48473.00000", "THIRD_INFORMATION_SOFTWARE": "6200", "AMOUNT_WATER": "12735.00000", "BUS_PASSENGER_AMOUNT": "58761.00000", "ELECTRICITY_AMOUNT": "2015351.00000", "THIRD_ADMINISTRATION_SOCIAL": "25000", "HIGHWAY_PASSENGER_AMOUNT": "3127.00000", "HIGHWAY_FREIGHT": "2258.00000", "INDUSTRY_CORP_VALUE_INNER": "4819201.00000", "INDUSTRY_CORP": "203.00000", "FIRST_ECOLOGICAL_PRACTITIONERS": "4400", "PROFIT_TOTAL": "118289.00000", "TWO_INDUSTRY_MANUFACT": "54600", "HOSPITAL_BEDS": "9500.00000", "THIRD_HEALTH_SOCIAL": "14200", "NET_WORTH_BALANCE": "2679021.00000", "TOTAL_FIXED_INVEST": "2213061.00000", "NUMBER_intERNET_USERS": "151588.00000", "GDP_GROWTH_RATE": "14.70000", "GDP": "4221885.00000", "BUDGET_PAY": "672512.00000", "GENERAL_BUDGET_REVENUE": "234468.00000", "RESIDENT_SAVINGS": "3956199.00000", "CITY_BUILD_AREA_PROPORTION": "17.37000", "CITY_RESIDENTS_LIVINGPOWER": "66412.00000", "CITY_PRIVATE_INDIVIDUAL_EMPLOYEES": "196828", "INDUSTRY_CORP_VALUE_OUTER": "607956.00000", "INDUSTRY_CORP_OUTER": "10", "PASSENGER_VOLUME": "3483.80000", "HOME_TOTAL_GAS_SUPPLY": "4513.00000", "PRIMARY_SCHOOL_TEACHERS": "8357", "PRIMARY_SCHOOL_STUDENTS": "16.56000", "PRIMARY_SCHOOL": "588", "THIRD_SERVICE_REPAIR": "400", "HOME_WATER_USE": "3450.00000", "INDUSTRY_SO_EMISSIONS": "67480.00000", "INDUSTRY_SOLID_WASTE_UTILIZATION": "73.79000", "INDUSTRY_WASTEWATER_EMISSION_STARD": "3463.00000", "INDUSTRY_WASTEWATER_EMISSION": "4139.00000", "INDUSTRY_SOOT_EMISSIONS": "23040.00000", "INDUSTRY_ELECTRICITY_AMOUNT": "1939428.00000", "TOWN_EMPLOYMENT_PERSONNEL": "24.66000", "TOWN_UNEMPLOYMENT_PERSONNEL": "23019", "ACTUAL_RENTAL_CAR_NUMBER": "5116", "ACTUAL_CITY_ROAD_AREA": "791.00000", "POPULATION": "217.79", "FINANCE_RMB_LOAN_BALANCE": "8573432.00000", "FINANCE_RMB_DEPOSIT_BALANCE": "9988212.00000", "BUILT_AREA_GREEN": "2350.00000", "BUILT_AREA": "66.00000", "TWO_INDUSTRY_CONSTRUCTION": "28000", "USE_FOREIGN_MONEY": "6693.00000", "THIRD_ESTATE": "5100", "ESTATE_INVEST_COMPLETE": "447164.00000", "THIRD_WHOLESALE_RETAIL": "12000", "THIRD_EDUCATION": "26400", "EDUCATION_PAY": "11.46450", "THIRD_CULTURAL_SPORTS_ENTERTAIN": "3800", "MIDDLE_SCHOOL_TEACHERS": "9500", "MIDDLE_SCHOOL_STUDENTS": "11.60000", "MIDDLE_SCHOOL": "145", "HIGH_SCHOOL_TEACHERS": "3368", "ORDINA_HIGH_SCHOOL_STUDENTS": "42177", "HIGH_SCHOOL": "8", "TELEPHONE_USERS": "70.10000", "DOMESTIC_VAT": "18.87210", "MILLION_WITH_BUS": "15", "MILLION_LIBRARY": "101", "CIVIL_AVIATION_PASSENGER": "45.82000", "CIVIL_AVIATION_FREIGHT": "6200.00000", "THIRD_WATER_PUBLIC": "5600", "CURRENT_ASSETS_YEARS_BALANCE": "2003103.00000", "LIQUIDGAS_TOTAL_AMOUNT": "63007.00000", "LIQUIDGAS_TOTAL_AMOUNT_HOME": "63000.00000", "HMT_INVEST_CORP_VALUE": "39774.00000", "HMT_INVEST_CORP": "5", "LIFE_GARBAGE_RATE": "100.00000", "LIFE_SEWAGE_RATE": "52.35000", "GAS_PEOPLE": "730000", "LIQUIDGAS_PEOPLE": "145000", "TELECOM_INCOME": "274193.00000", "TWO_INDUSTRY_ELECTRIC": "6600", "SOCIOLOGY_CONSUMER_QUOTA": "1699948.00000", "SCIENCE_PAY": "1.40690", "THIRD_SCIENTIFIC_SERVICE_GEOLOGY": "9300", "THIRD_LEASE_BUSINESS": "6800", "MOBILE_PHONE_USERS": "108.66000", "FIRST_PEOPLE_PROPORTION": "1.78000", "FIRST_INDUSTRY_GDP": "4.55000", "THIRD_PEOPLE_PROPORTION": "60.50000", "THIRD_INDUSTRY_GDP": "41.59000", "TWO_PEOPLE_PROPORTION": "37.71000", "TWO_INDUSTRY_GDP": "53.86000", "WORKER_AVERAGE_WAGE": "2.64617", "NATURAL_POPULATION_GROWTH_RATE": "6.57000", "ADMINISTRATION_AREA": "7649.00000", "ABOVE_INDUSTRY_CORP": "218", "ABOVE_INDUSTRY_CORP_VALUE": "5466931.00000", "RAILWAY_TOTAL_FREIGHT": "2641.62000", "POSTAL_INCOME": "11848.00000", "TWO_MINE": "3800", "THIRD_FINANCE": "9900", "RAILWAY_PASSENGER_AMOUNT": "311.00000", "RAILWAY_FREIGHT": "383.00000", "HIGH_SCHOOL_STUDENTS": "46437"}, "630121": {"ADMINISTRATIVE_CODE": "630121", "PROVINCE": "\u9752\u6d77\u7701", "CITY": "\u897f\u5b81\u5e02", "COUNTY": "\u5927\u901a\u56de\u65cf\u571f\u65cf\u81ea\u6cbb\u53bf", "STATISTICAL_YEAR": "2008", "HOSPITAL_BEDS": "1041.00000", "BUDGET_PAY": "95694.00000", "GENERAL_BUDGET_REVENUE": "25320.00000", "RESIDENT_SAVINGS": "216083.00000", "PRIMARY_SCHOOL_STUDENTS": "4.24810", "POPULATION": "45.00", "FINANCE_RMB_LOAN_BALANCE": "419484.00000", "MIDDLE_SCHOOL_STUDENTS": "2.45210", "TELEPHONE_USERS": "5.97940", "ADMINISTRATION_AREA": "3090.00000", "ABOVE_INDUSTRY_CORP": "31", "ABOVE_INDUSTRY_CORP_VALUE": "1310467.00000", "TOWNSHIP": "20", "VILLAGERS_COMMITTEE": "289", "TOTAL_HOMES": "114956", "RURAL_HOMES": "8.08320", "RURAL_POPULATION": "35.00", "PRACTITIONERS": "38765", "RURAL_PRACTITIONERS": "20.35550", "AGRICULTURAL_MACHINERY": "39", "FIRST_ADD_VALUE": "66606.00000", "TWO_ADD_VALUE": "524758.00000", "FOOD_YIELD": "78186.00000", "OIL_YIELD": "55945.00000", "MEAT_YIELD": "28859.00000", "BUILD_INVEST_QUOTA": "85.00000", "SOCIAL_WELFARE_INSTITUTE": "6", "SOCIAL_WELFARE_INSTITUTE_BED": "120", "FIRST_INDUSTRY_PERSONNEL": "8.8215"}, "630106": {"ADMINISTRATIVE_CODE": "630106", "PROVINCE": "\u9752\u6d77\u7701", "CITY": "\u897f\u5b81\u5e02", "COUNTY": "\u6e5f\u4e2d\u533a", "STATISTICAL_YEAR": "2008", "HOSPITAL_BEDS": "579.00000", "BUDGET_PAY": "95007.00000", "GENERAL_BUDGET_REVENUE": "5023.00000", "RESIDENT_SAVINGS": "130079.00000", "PRIMARY_SCHOOL_STUDENTS": "4.14080", "POPULATION": "46.00", "FINANCE_RMB_LOAN_BALANCE": "84205.00000", "MIDDLE_SCHOOL_STUDENTS": "2.63420", "TELEPHONE_USERS": "3.84470", "ADMINISTRATION_AREA": "2430.00000", "ABOVE_INDUSTRY_CORP": "33", "ABOVE_INDUSTRY_CORP_VALUE": "998200.00000", "TOWNSHIP": "15", "VILLAGERS_COMMITTEE": "393", "TOTAL_HOMES": "124343", "RURAL_HOMES": "9.74750", "RURAL_POPULATION": "42.00", "PRACTITIONERS": "19930", "RURAL_PRACTITIONERS": "25.13090", "AGRICULTURAL_MACHINERY": "65", "FIRST_ADD_VALUE": "74911.00000", "TWO_ADD_VALUE": "452233.00000", "FOOD_YIELD": "146748.00000", "OIL_YIELD": "43084.00000", "MEAT_YIELD": "20190.00000", "BUILD_INVEST_QUOTA": "27.00000", "FIRST_INDUSTRY_PERSONNEL": "12.1933"}, "630123": {"ADMINISTRATIVE_CODE": "630123", "PROVINCE": "\u9752\u6d77\u7701", "CITY": "\u897f\u5b81\u5e02", "COUNTY": "\u6e5f\u6e90\u53bf", "STATISTICAL_YEAR": "2008", "HOSPITAL_BEDS": "377.00000", "BUDGET_PAY": "34803.00000", "GENERAL_BUDGET_REVENUE": "4988.00000", "RESIDENT_SAVINGS": "74521.00000", "PRIMARY_SCHOOL_STUDENTS": "1.04240", "POPULATION": "14.00", "FINANCE_RMB_LOAN_BALANCE": "38592.00000", "MIDDLE_SCHOOL_STUDENTS": "0.90870", "TELEPHONE_USERS": "2.53530", "ADMINISTRATION_AREA": "1509.00000", "ABOVE_INDUSTRY_CORP": "16", "ABOVE_INDUSTRY_CORP_VALUE": "167746.00000", "TOWNSHIP": "9", "VILLAGERS_COMMITTEE": "146", "TOTAL_HOMES": "41098", "RURAL_HOMES": "2.55050", "RURAL_POPULATION": "11.00", "PRACTITIONERS": "8300", "RURAL_PRACTITIONERS": "5.77700", "AGRICULTURAL_MACHINERY": "17", "FIRST_ADD_VALUE": "24582.00000", "TWO_ADD_VALUE": "86076.00000", "FOOD_YIELD": "30411.00000", "OIL_YIELD": "7071.00000", "MEAT_YIELD": "8354.00000", "BUILD_INVEST_QUOTA": "40.00000", "SOCIAL_WELFARE_INSTITUTE": "1", "SOCIAL_WELFARE_INSTITUTE_BED": "16", "FIRST_INDUSTRY_PERSONNEL": "4.6848"}, "630203": {"ADMINISTRATIVE_CODE": "630203", "PROVINCE": "\u9752\u6d77\u7701", "CITY": "\u6d77\u4e1c\u5e02", "COUNTY": "\u5e73\u5b89\u533a", "STATISTICAL_YEAR": "2008", "HOSPITAL_BEDS": "283.00000", "BUDGET_PAY": "41721.00000", "GENERAL_BUDGET_REVENUE": "4337.00000", "RESIDENT_SAVINGS": "114952.00000", "PRIMARY_SCHOOL_STUDENTS": "0.94140", "POPULATION": "12.00", "FINANCE_RMB_LOAN_BALANCE": "125298.00000", "MIDDLE_SCHOOL_STUDENTS": "0.78410", "TELEPHONE_USERS": "2.58890", "ADMINISTRATION_AREA": "750.00000", "ABOVE_INDUSTRY_CORP": "12", "ABOVE_INDUSTRY_CORP_VALUE": "171887.00000", "TOWNSHIP": "8", "VILLAGERS_COMMITTEE": "111", "TOTAL_HOMES": "36975", "RURAL_HOMES": "1.84470", "RURAL_POPULATION": "8.00", "PRACTITIONERS": "5151", "RURAL_PRACTITIONERS": "4.36240", "AGRICULTURAL_MACHINERY": "6", "FIRST_ADD_VALUE": "18462.00000", "TWO_ADD_VALUE": "83216.00000", "FOOD_YIELD": "47446.00000", "OIL_YIELD": "11414.00000", "MEAT_YIELD": "4949.00000", "BUILD_INVEST_QUOTA": "85460.00000", "SOCIAL_WELFARE_INSTITUTE": "1", "SOCIAL_WELFARE_INSTITUTE_BED": "39", "FIRST_INDUSTRY_PERSONNEL": "2.3388"}, "630222": {"ADMINISTRATIVE_CODE": "630222", "PROVINCE": "\u9752\u6d77\u7701", "CITY": "\u6d77\u4e1c\u5e02", "COUNTY": "\u6c11\u548c\u56de\u65cf\u571f\u65cf\u81ea\u6cbb\u53bf", "STATISTICAL_YEAR": "2008", "HOSPITAL_BEDS": "578.00000", "BUDGET_PAY": "77929.00000", "GENERAL_BUDGET_REVENUE": "8007.00000", "RESIDENT_SAVINGS": "115328.00000", "PRIMARY_SCHOOL_STUDENTS": "4.24740", "POPULATION": "40.00", "FINANCE_RMB_LOAN_BALANCE": "36993.00000", "MIDDLE_SCHOOL_STUDENTS": "2.93610", "TELEPHONE_USERS": "11.94110", "ADMINISTRATION_AREA": "1780.00000", "ABOVE_INDUSTRY_CORP": "25", "ABOVE_INDUSTRY_CORP_VALUE": "121333.00000", "TOWNSHIP": "22", "VILLAGERS_COMMITTEE": "312", "TOTAL_HOMES": "97410", "RURAL_HOMES": "7.27960", "RURAL_POPULATION": "35.00", "PRACTITIONERS": "11822", "RURAL_PRACTITIONERS": "17.16150", "AGRICULTURAL_MACHINERY": "28", "FIRST_ADD_VALUE": "44665.00000", "TWO_ADD_VALUE": "83398.00000", "FOOD_YIELD": "116367.00000", "OIL_YIELD": "22901.00000", "MEAT_YIELD": "12464.00000", "BUILD_INVEST_QUOTA": "72756.00000", "FIRST_INDUSTRY_PERSONNEL": "8.6143"}, "630202": {"ADMINISTRATIVE_CODE": "630202", "PROVINCE": "\u9752\u6d77\u7701", "CITY": "\u6d77\u4e1c\u5e02", "COUNTY": "\u4e50\u90fd\u533a", "STATISTICAL_YEAR": "2008", "HOSPITAL_BEDS": "345.00000", "BUDGET_PAY": "78399.00000", "GENERAL_BUDGET_REVENUE": "4655.00000", "RESIDENT_SAVINGS": "145595.00000", "PRIMARY_SCHOOL_STUDENTS": "1.95120", "POPULATION": "29.00", "FINANCE_RMB_LOAN_BALANCE": "36547.00000", "MIDDLE_SCHOOL_STUDENTS": "2.04500", "TELEPHONE_USERS": "4.81560", "ADMINISTRATION_AREA": "3050.00000", "ABOVE_INDUSTRY_CORP": "15", "ABOVE_INDUSTRY_CORP_VALUE": "115233.00000", "TOWNSHIP": "19", "VILLAGERS_COMMITTEE": "354", "TOTAL_HOMES": "84182", "RURAL_HOMES": "5.84910", "RURAL_POPULATION": "24.00", "PRACTITIONERS": "9923", "RURAL_PRACTITIONERS": "13.14380", "AGRICULTURAL_MACHINERY": "21", "FIRST_ADD_VALUE": "51219.00000", "TWO_ADD_VALUE": "68140.00000", "FOOD_YIELD": "64130.00000", "OIL_YIELD": "5685.00000", "MEAT_YIELD": "22324.00000", "BUILD_INVEST_QUOTA": "89446.00000", "FIRST_INDUSTRY_PERSONNEL": "6.0601"}, "630223": {"ADMINISTRATIVE_CODE": "630223", "PROVINCE": "\u9752\u6d77\u7701", "CITY": "\u6d77\u4e1c\u5e02", "COUNTY": "\u4e92\u52a9\u571f\u65cf\u81ea\u6cbb\u53bf", "STATISTICAL_YEAR": "2008", "HOSPITAL_BEDS": "435.00000", "BUDGET_PAY": "92948.00000", "GENERAL_BUDGET_REVENUE": "7226.00000", "RESIDENT_SAVINGS": "113614.00000", "PRIMARY_SCHOOL_STUDENTS": "2.96360", "POPULATION": "38.00", "FINANCE_RMB_LOAN_BALANCE": "60381.00000", "MIDDLE_SCHOOL_STUDENTS": "2.42160", "TELEPHONE_USERS": "2.84160", "ADMINISTRATION_AREA": "3321.00000", "ABOVE_INDUSTRY_CORP": "26", "ABOVE_INDUSTRY_CORP_VALUE": "140792.00000", "TOWNSHIP": "19", "VILLAGERS_COMMITTEE": "294", "TOTAL_HOMES": "98234", "RURAL_HOMES": "8.08810", "RURAL_POPULATION": "34.00", "PRACTITIONERS": "18134", "RURAL_PRACTITIONERS": "18.17470", "AGRICULTURAL_MACHINERY": "39", "FIRST_ADD_VALUE": "80736.00000", "TWO_ADD_VALUE": "89642.00000", "FOOD_YIELD": "138808.00000", "OIL_YIELD": "61460.00000", "MEAT_YIELD": "27404.00000", "BUILD_INVEST_QUOTA": "94816.00000", "SOCIAL_WELFARE_INSTITUTE": "1", "SOCIAL_WELFARE_INSTITUTE_BED": "24", "FIRST_INDUSTRY_PERSONNEL": "11.2860"}, "630224": {"ADMINISTRATIVE_CODE": "630224", "PROVINCE": "\u9752\u6d77\u7701", "CITY": "\u6d77\u4e1c\u5e02", "COUNTY": "\u5316\u9686\u56de\u65cf\u81ea\u6cbb\u53bf", "STATISTICAL_YEAR": "2008", "HOSPITAL_BEDS": "219.00000", "BUDGET_PAY": "56587.00000", "GENERAL_BUDGET_REVENUE": "5067.00000", "RESIDENT_SAVINGS": "53778.00000", "PRIMARY_SCHOOL_STUDENTS": "2.44990", "POPULATION": "25.00", "FINANCE_RMB_LOAN_BALANCE": "27957.00000", "MIDDLE_SCHOOL_STUDENTS": "1.08360", "TELEPHONE_USERS": "6.63670", "ADMINISTRATION_AREA": "2740.00000", "ABOVE_INDUSTRY_CORP": "9", "ABOVE_INDUSTRY_CORP_VALUE": "246283.00000", "TOWNSHIP": "19", "VILLAGERS_COMMITTEE": "362", "TOTAL_HOMES": "57814", "RURAL_HOMES": "4.45950", "RURAL_POPULATION": "22.00", "PRACTITIONERS": "5975", "RURAL_PRACTITIONERS": "11.47340", "AGRICULTURAL_MACHINERY": "20", "FIRST_ADD_VALUE": "28941.00000", "TWO_ADD_VALUE": "113254.00000", "FOOD_YIELD": "59545.00000", "OIL_YIELD": "24349.00000", "MEAT_YIELD": "10124.00000", "BUILD_INVEST_QUOTA": "17367.00000", "FIRST_INDUSTRY_PERSONNEL": "7.3207"}, "630225": {"ADMINISTRATIVE_CODE": "630225", "PROVINCE": "\u9752\u6d77\u7701", "CITY": "\u6d77\u4e1c\u5e02", "COUNTY": "\u5faa\u5316\u6492\u62c9\u65cf\u81ea\u6cbb\u53bf", "STATISTICAL_YEAR": "2008", "HOSPITAL_BEDS": "108.00000", "BUDGET_PAY": "44078.00000", "GENERAL_BUDGET_REVENUE": "4241.00000", "RESIDENT_SAVINGS": "64706.00000", "PRIMARY_SCHOOL_STUDENTS": "1.48230", "POPULATION": "13.00", "FINANCE_RMB_LOAN_BALANCE": "22896.00000", "MIDDLE_SCHOOL_STUDENTS": "0.66270", "TELEPHONE_USERS": "1.34990", "ADMINISTRATION_AREA": "1750.00000", "ABOVE_INDUSTRY_CORP": "7", "ABOVE_INDUSTRY_CORP_VALUE": "28474.00000", "TOWNSHIP": "9", "VILLAGERS_COMMITTEE": "154", "TOTAL_HOMES": "33587", "RURAL_HOMES": "2.34120", "RURAL_POPULATION": "12.00", "PRACTITIONERS": "5981", "RURAL_PRACTITIONERS": "5.24000", "AGRICULTURAL_MACHINERY": "8", "FIRST_ADD_VALUE": "20074.00000", "TWO_ADD_VALUE": "26266.00000", "FOOD_YIELD": "31955.00000", "OIL_YIELD": "7336.00000", "MEAT_YIELD": "6729.00000", "BUILD_INVEST_QUOTA": "42609.00000", "SOCIAL_WELFARE_INSTITUTE": "4", "SOCIAL_WELFARE_INSTITUTE_BED": "79", "FIRST_INDUSTRY_PERSONNEL": "0.0397"}, "632221": {"ADMINISTRATIVE_CODE": "632221", "PROVINCE": "\u9752\u6d77\u7701", "CITY": "\u6d77\u5317\u85cf\u65cf\u81ea\u6cbb\u5dde", "COUNTY": "\u95e8\u6e90\u56de\u65cf\u81ea\u6cbb\u53bf", "STATISTICAL_YEAR": "2008", "HOSPITAL_BEDS": "156.00000", "BUDGET_PAY": "37866.00000", "GENERAL_BUDGET_REVENUE": "3402.00000", "RESIDENT_SAVINGS": "57971.00000", "PRIMARY_SCHOOL_STUDENTS": "1.80740", "POPULATION": "15.00", "FINANCE_RMB_LOAN_BALANCE": "15304.00000", "MIDDLE_SCHOOL_STUDENTS": "0.81820", "TELEPHONE_USERS": "1.37900", "ADMINISTRATION_AREA": "7167.00000", "ABOVE_INDUSTRY_CORP": "22", "ABOVE_INDUSTRY_CORP_VALUE": "27729.00000", "TOWNSHIP": "12", "VILLAGERS_COMMITTEE": "109", "TOTAL_HOMES": "40366", "RURAL_HOMES": "2.73450", "RURAL_POPULATION": "13.00", "PRACTITIONERS": "7728", "RURAL_PRACTITIONERS": "6.91150", "AGRICULTURAL_MACHINERY": "14", "FIRST_ADD_VALUE": "37140.00000", "TWO_ADD_VALUE": "41098.00000", "FOOD_YIELD": "31648.00000", "OIL_YIELD": "37159.00000", "MEAT_YIELD": "9940.00000", "BUILD_INVEST_QUOTA": "44307.00000", "FIRST_INDUSTRY_PERSONNEL": "4.8859"}, "632222": {"ADMINISTRATIVE_CODE": "632222", "PROVINCE": "\u9752\u6d77\u7701", "CITY": "\u6d77\u5317\u85cf\u65cf\u81ea\u6cbb\u5dde", "COUNTY": "\u7941\u8fde\u53bf", "STATISTICAL_YEAR": "2008", "HOSPITAL_BEDS": "113.00000", "BUDGET_PAY": "21944.00000", "GENERAL_BUDGET_REVENUE": "2036.00000", "RESIDENT_SAVINGS": "19432.00000", "PRIMARY_SCHOOL_STUDENTS": "0.65010", "POPULATION": "5.00", "FINANCE_RMB_LOAN_BALANCE": "11650.00000", "MIDDLE_SCHOOL_STUDENTS": "0.27980", "TELEPHONE_USERS": "0.62140", "ADMINISTRATION_AREA": "14681.00000", "ABOVE_INDUSTRY_CORP": "13", "ABOVE_INDUSTRY_CORP_VALUE": "11150.00000", "TOWNSHIP": "7", "VILLAGERS_COMMITTEE": "45", "TOTAL_HOMES": "14925", "RURAL_HOMES": "0.85920", "RURAL_POPULATION": "4.00", "PRACTITIONERS": "3516", "RURAL_PRACTITIONERS": "2.01070", "AGRICULTURAL_MACHINERY": "4", "FIRST_ADD_VALUE": "22701.00000", "TWO_ADD_VALUE": "22756.00000", "FOOD_YIELD": "3826.00000", "OIL_YIELD": "1143.00000", "MEAT_YIELD": "12232.00000", "BUILD_INVEST_QUOTA": "34770.00000", "FIRST_INDUSTRY_PERSONNEL": "1.5396"}, "632223": {"ADMINISTRATIVE_CODE": "632223", "PROVINCE": "\u9752\u6d77\u7701", "CITY": "\u6d77\u5317\u85cf\u65cf\u81ea\u6cbb\u5dde", "COUNTY": "\u6d77\u664f\u53bf", "STATISTICAL_YEAR": "2008", "HOSPITAL_BEDS": "449.00000", "BUDGET_PAY": "54676.00000", "GENERAL_BUDGET_REVENUE": "5014.00000", "RESIDENT_SAVINGS": "37394.00000", "PRIMARY_SCHOOL_STUDENTS": "4317.00000", "POPULATION": "3.00", "FINANCE_RMB_LOAN_BALANCE": "50496.00000", "MIDDLE_SCHOOL_STUDENTS": "0.26530", "TELEPHONE_USERS": "0.84820", "ADMINISTRATION_AREA": "4067.00000", "ABOVE_INDUSTRY_CORP": "14", "ABOVE_INDUSTRY_CORP_VALUE": "111356.00000", "TOWNSHIP": "5", "VILLAGERS_COMMITTEE": "29", "TOTAL_HOMES": "11158", "RURAL_HOMES": "0.50400", "RURAL_POPULATION": "2.00", "PRACTITIONERS": "9837", "RURAL_PRACTITIONERS": "1.27910", "AGRICULTURAL_MACHINERY": "3", "FIRST_ADD_VALUE": "8686.00000", "TWO_ADD_VALUE": "96611.00000", "FOOD_YIELD": "4347.00000", "OIL_YIELD": "967.00000", "MEAT_YIELD": "5330.00000", "BUILD_INVEST_QUOTA": "104210.00000", "FIRST_INDUSTRY_PERSONNEL": "0.9227"}, "632224": {"ADMINISTRATIVE_CODE": "632224", "PROVINCE": "\u9752\u6d77\u7701", "CITY": "\u6d77\u5317\u85cf\u65cf\u81ea\u6cbb\u5dde", "COUNTY": "\u521a\u5bdf\u53bf", "STATISTICAL_YEAR": "2008", "HOSPITAL_BEDS": "92.00000", "BUDGET_PAY": "22197.00000", "GENERAL_BUDGET_REVENUE": "1548.00000", "RESIDENT_SAVINGS": "13829.00000", "PRIMARY_SCHOOL_STUDENTS": "0.43710", "POPULATION": "4.00", "FINANCE_RMB_LOAN_BALANCE": "9381.00000", "MIDDLE_SCHOOL_STUDENTS": "0.15670", "TELEPHONE_USERS": "0.37330", "ADMINISTRATION_AREA": "8153.00000", "ABOVE_INDUSTRY_CORP": "3", "ABOVE_INDUSTRY_CORP_VALUE": "2625.00000", "TOWNSHIP": "5", "VILLAGERS_COMMITTEE": "31", "TOTAL_HOMES": "13248", "RURAL_HOMES": "0.58040", "RURAL_POPULATION": "3.00", "PRACTITIONERS": "3793", "RURAL_PRACTITIONERS": "1.25780", "AGRICULTURAL_MACHINERY": "2", "FIRST_ADD_VALUE": "20401.00000", "TWO_ADD_VALUE": "7394.00000", "FOOD_YIELD": "1212.00000", "OIL_YIELD": "7288.00000", "MEAT_YIELD": "10635.00000", "BUILD_INVEST_QUOTA": "6938.00000", "FIRST_INDUSTRY_PERSONNEL": "1.1524"}, "632301": {"ADMINISTRATIVE_CODE": "632301", "PROVINCE": "\u9752\u6d77\u7701", "CITY": "\u9ec4\u5357\u85cf\u65cf\u81ea\u6cbb\u5dde", "COUNTY": "\u540c\u4ec1\u5e02", "STATISTICAL_YEAR": "2008", "HOSPITAL_BEDS": "33.00000", "BUDGET_PAY": "31053.00000", "GENERAL_BUDGET_REVENUE": "1817.00000", "RESIDENT_SAVINGS": "45477.00000", "PRIMARY_SCHOOL_STUDENTS": "1.15990", "POPULATION": "8.00", "FINANCE_RMB_LOAN_BALANCE": "23870.00000", "MIDDLE_SCHOOL_STUDENTS": "1.05900", "TELEPHONE_USERS": "0.99880", "ADMINISTRATION_AREA": "3275.00000", "ABOVE_INDUSTRY_CORP": "1", "ABOVE_INDUSTRY_CORP_VALUE": "1704.00000", "TOWNSHIP": "12", "VILLAGERS_COMMITTEE": "72", "TOTAL_HOMES": "21538", "RURAL_HOMES": "1.21960", "RURAL_POPULATION": "6.00", "PRACTITIONERS": "7673", "RURAL_PRACTITIONERS": "3.39400", "AGRICULTURAL_MACHINERY": "4", "FIRST_ADD_VALUE": "23190.00000", "TWO_ADD_VALUE": "10218.00000", "FOOD_YIELD": "14677.00000", "OIL_YIELD": "3306.00000", "MEAT_YIELD": "3581.00000", "BUILD_INVEST_QUOTA": "18608.00000", "SOCIAL_WELFARE_INSTITUTE": "1", "SOCIAL_WELFARE_INSTITUTE_BED": "20", "FIRST_INDUSTRY_PERSONNEL": "2.7053"}, "632322": {"ADMINISTRATIVE_CODE": "632322", "PROVINCE": "\u9752\u6d77\u7701", "CITY": "\u9ec4\u5357\u85cf\u65cf\u81ea\u6cbb\u5dde", "COUNTY": "\u5c16\u624e\u53bf", "STATISTICAL_YEAR": "2008", "HOSPITAL_BEDS": "197.00000", "BUDGET_PAY": "6347.00000", "GENERAL_BUDGET_REVENUE": "4611.00000", "RESIDENT_SAVINGS": "32169.00000", "PRIMARY_SCHOOL_STUDENTS": "0.69950", "POPULATION": "6.00", "FINANCE_RMB_LOAN_BALANCE": "23574.00000", "MIDDLE_SCHOOL_STUDENTS": "0.41780", "TELEPHONE_USERS": "0.61000", "ADMINISTRATION_AREA": "2174.00000", "ABOVE_INDUSTRY_CORP": "7", "ABOVE_INDUSTRY_CORP_VALUE": "254408.00000", "TOWNSHIP": "9", "VILLAGERS_COMMITTEE": "81", "TOTAL_HOMES": "18133", "RURAL_HOMES": "0.90830", "RURAL_POPULATION": "4.00", "PRACTITIONERS": "5232", "RURAL_PRACTITIONERS": "2.13680", "AGRICULTURAL_MACHINERY": "5", "FIRST_ADD_VALUE": "12700.00000", "TWO_ADD_VALUE": "115235.00000", "FOOD_YIELD": "13892.00000", "OIL_YIELD": "586.00000", "MEAT_YIELD": "3151.00000", "BUILD_INVEST_QUOTA": "35150.00000", "SOCIAL_WELFARE_INSTITUTE_BED": "5", "FIRST_INDUSTRY_PERSONNEL": "1.4663"}, "632323": {"ADMINISTRATIVE_CODE": "632323", "PROVINCE": "\u9752\u6d77\u7701", "CITY": "\u9ec4\u5357\u85cf\u65cf\u81ea\u6cbb\u5dde", "COUNTY": "\u6cfd\u5e93\u53bf", "STATISTICAL_YEAR": "2008", "HOSPITAL_BEDS": "81.00000", "BUDGET_PAY": "26962.00000", "GENERAL_BUDGET_REVENUE": "272.00000", "RESIDENT_SAVINGS": "6979.00000", "PRIMARY_SCHOOL_STUDENTS": "0.92530", "POPULATION": "7.00", "FINANCE_RMB_LOAN_BALANCE": "6020.00000", "MIDDLE_SCHOOL_STUDENTS": "0.17100", "TELEPHONE_USERS": "0.20000", "ADMINISTRATION_AREA": "6986.00000", "TOWNSHIP": "7", "VILLAGERS_COMMITTEE": "64", "TOTAL_HOMES": "18175", "RURAL_HOMES": "1.32130", "RURAL_POPULATION": "6.00", "PRACTITIONERS": "1783", "RURAL_PRACTITIONERS": "2.69610", "AGRICULTURAL_MACHINERY": "1", "FIRST_ADD_VALUE": "34448.00000", "TWO_ADD_VALUE": "3939.00000", "OIL_YIELD": "1952.00000", "MEAT_YIELD": "14035.00000", "BUILD_INVEST_QUOTA": "18734.00000", "SOCIAL_WELFARE_INSTITUTE": "2", "SOCIAL_WELFARE_INSTITUTE_BED": "38", "FIRST_INDUSTRY_PERSONNEL": "2.4854"}, "632324": {"ADMINISTRATIVE_CODE": "632324", "PROVINCE": "\u9752\u6d77\u7701", "CITY": "\u9ec4\u5357\u85cf\u65cf\u81ea\u6cbb\u5dde", "COUNTY": "\u6cb3\u5357\u8499\u53e4\u65cf\u81ea\u6cbb\u53bf", "STATISTICAL_YEAR": "2008", "HOSPITAL_BEDS": "148.00000", "BUDGET_PAY": "20189.00000", "GENERAL_BUDGET_REVENUE": "658.00000", "RESIDENT_SAVINGS": "9546.00000", "PRIMARY_SCHOOL_STUDENTS": "0.47410", "POPULATION": "4.00", "FINANCE_RMB_LOAN_BALANCE": "5856.00000", "MIDDLE_SCHOOL_STUDENTS": "0.18870", "TELEPHONE_USERS": "0.18000", "ADMINISTRATION_AREA": "6998.00000", "ABOVE_INDUSTRY_CORP": "6", "ABOVE_INDUSTRY_CORP_VALUE": "4214.00000", "TOWNSHIP": "5", "VILLAGERS_COMMITTEE": "39", "TOTAL_HOMES": "9593", "RURAL_HOMES": "0.58410", "RURAL_POPULATION": "3.00", "PRACTITIONERS": "2005", "RURAL_PRACTITIONERS": "1.56090", "FIRST_ADD_VALUE": "35276.00000", "TWO_ADD_VALUE": "6617.00000", "MEAT_YIELD": "12825.00000", "BUILD_INVEST_QUOTA": "29174.00000", "SOCIAL_WELFARE_INSTITUTE": "1", "SOCIAL_WELFARE_INSTITUTE_BED": "30", "FIRST_INDUSTRY_PERSONNEL": "1.4950"}, "632521": {"ADMINISTRATIVE_CODE": "632521", "PROVINCE": "\u9752\u6d77\u7701", "CITY": "\u6d77\u5357\u85cf\u65cf\u81ea\u6cbb\u5dde", "COUNTY": "\u5171\u548c\u53bf", "STATISTICAL_YEAR": "2008", "HOSPITAL_BEDS": "584.00000", "BUDGET_PAY": "40384.00000", "GENERAL_BUDGET_REVENUE": "4243.00000", "RESIDENT_SAVINGS": "92504.00000", "PRIMARY_SCHOOL_STUDENTS": "1.49640", "POPULATION": "13.00", "FINANCE_RMB_LOAN_BALANCE": "29946.00000", "MIDDLE_SCHOOL_STUDENTS": "0.37140", "TELEPHONE_USERS": "2.28440", "ADMINISTRATION_AREA": "17209.00000", "ABOVE_INDUSTRY_CORP": "13", "ABOVE_INDUSTRY_CORP_VALUE": "144107.00000", "TOWNSHIP": "11", "VILLAGERS_COMMITTEE": "100", "TOTAL_HOMES": "42529", "RURAL_HOMES": "1.86140", "RURAL_POPULATION": "9.00", "PRACTITIONERS": "11497", "RURAL_PRACTITIONERS": "4.43000", "AGRICULTURAL_MACHINERY": "12", "FIRST_ADD_VALUE": "35680.00000", "TWO_ADD_VALUE": "86580.00000", "FOOD_YIELD": "37725.00000", "OIL_YIELD": "11984.00000", "MEAT_YIELD": "17045.00000", "BUILD_INVEST_QUOTA": "41889.00000", "SOCIAL_WELFARE_INSTITUTE": "3", "SOCIAL_WELFARE_INSTITUTE_BED": "106", "FIRST_INDUSTRY_PERSONNEL": "3.4945"}, "632522": {"ADMINISTRATIVE_CODE": "632522", "PROVINCE": "\u9752\u6d77\u7701", "CITY": "\u6d77\u5357\u85cf\u65cf\u81ea\u6cbb\u5dde", "COUNTY": "\u540c\u5fb7\u53bf", "STATISTICAL_YEAR": "2008", "HOSPITAL_BEDS": "131.00000", "BUDGET_PAY": "25929.00000", "GENERAL_BUDGET_REVENUE": "684.00000", "RESIDENT_SAVINGS": "8231.00000", "PRIMARY_SCHOOL_STUDENTS": "0.84110", "POPULATION": "6.00", "FINANCE_RMB_LOAN_BALANCE": "7633.00000", "MIDDLE_SCHOOL_STUDENTS": "0.28000", "TELEPHONE_USERS": "0.43000", "ADMINISTRATION_AREA": "5001.00000", "ABOVE_INDUSTRY_CORP": "2", "ABOVE_INDUSTRY_CORP_VALUE": "334.00000", "TOWNSHIP": "5", "VILLAGERS_COMMITTEE": "73", "TOTAL_HOMES": "13621", "RURAL_HOMES": "0.87810", "RURAL_POPULATION": "5.00", "PRACTITIONERS": "3085", "RURAL_PRACTITIONERS": "2.46020", "AGRICULTURAL_MACHINERY": "5", "FIRST_ADD_VALUE": "33378.00000", "TWO_ADD_VALUE": "10660.00000", "FOOD_YIELD": "8350.00000", "OIL_YIELD": "3941.00000", "MEAT_YIELD": "9279.00000", "BUILD_INVEST_QUOTA": "13149.00000", "FIRST_INDUSTRY_PERSONNEL": "2.1649"}, "632523": {"ADMINISTRATIVE_CODE": "632523", "PROVINCE": "\u9752\u6d77\u7701", "CITY": "\u6d77\u5357\u85cf\u65cf\u81ea\u6cbb\u5dde", "COUNTY": "\u8d35\u5fb7\u53bf", "STATISTICAL_YEAR": "2008", "HOSPITAL_BEDS": "257.00000", "BUDGET_PAY": "34085.00000", "GENERAL_BUDGET_REVENUE": "4754.00000", "RESIDENT_SAVINGS": "73055.00000", "PRIMARY_SCHOOL_STUDENTS": "1.07040", "POPULATION": "10.00", "FINANCE_RMB_LOAN_BALANCE": "13989.00000", "MIDDLE_SCHOOL_STUDENTS": "0.59670", "TELEPHONE_USERS": "1.48000", "ADMINISTRATION_AREA": "3504.00000", "ABOVE_INDUSTRY_CORP": "4", "ABOVE_INDUSTRY_CORP_VALUE": "65278.00000", "TOWNSHIP": "7", "VILLAGERS_COMMITTEE": "119", "TOTAL_HOMES": "29851", "RURAL_HOMES": "1.98430", "RURAL_POPULATION": "8.00", "PRACTITIONERS": "3703", "RURAL_PRACTITIONERS": "4.52890", "AGRICULTURAL_MACHINERY": "7", "FIRST_ADD_VALUE": "15548.00000", "TWO_ADD_VALUE": "71668.00000", "FOOD_YIELD": "27116.00000", "OIL_YIELD": "8685.00000", "MEAT_YIELD": "4419.00000", "BUILD_INVEST_QUOTA": "28422.00000", "SOCIAL_WELFARE_INSTITUTE": "2", "SOCIAL_WELFARE_INSTITUTE_BED": "50", "FIRST_INDUSTRY_PERSONNEL": "2.0645"}, "632524": {"ADMINISTRATIVE_CODE": "632524", "PROVINCE": "\u9752\u6d77\u7701", "CITY": "\u6d77\u5357\u85cf\u65cf\u81ea\u6cbb\u5dde", "COUNTY": "\u5174\u6d77\u53bf", "STATISTICAL_YEAR": "2008", "HOSPITAL_BEDS": "75.00000", "BUDGET_PAY": "30414.00000", "GENERAL_BUDGET_REVENUE": "3054.00000", "RESIDENT_SAVINGS": "11721.00000", "PRIMARY_SCHOOL_STUDENTS": "0.84080", "POPULATION": "7.00", "FINANCE_RMB_LOAN_BALANCE": "8566.00000", "MIDDLE_SCHOOL_STUDENTS": "0.20500", "TELEPHONE_USERS": "0.56000", "ADMINISTRATION_AREA": "12182.00000", "ABOVE_INDUSTRY_CORP": "3", "ABOVE_INDUSTRY_CORP_VALUE": "36326.00000", "TOWNSHIP": "7", "VILLAGERS_COMMITTEE": "57", "TOTAL_HOMES": "16540", "RURAL_HOMES": "11468.00000", "RURAL_POPULATION": "6.00", "PRACTITIONERS": "3251", "RURAL_PRACTITIONERS": "2.49000", "AGRICULTURAL_MACHINERY": "2", "FIRST_ADD_VALUE": "32514.00000", "TWO_ADD_VALUE": "38586.00000", "FOOD_YIELD": "12072.00000", "OIL_YIELD": "5447.00000", "MEAT_YIELD": "11573.00000", "BUILD_INVEST_QUOTA": "32934.00000", "SOCIAL_WELFARE_INSTITUTE": "1", "FIRST_INDUSTRY_PERSONNEL": "2.3846"}, "632525": {"ADMINISTRATIVE_CODE": "632525", "PROVINCE": "\u9752\u6d77\u7701", "CITY": "\u6d77\u5357\u85cf\u65cf\u81ea\u6cbb\u5dde", "COUNTY": "\u8d35\u5357\u53bf", "STATISTICAL_YEAR": "2008", "HOSPITAL_BEDS": "197.00000", "BUDGET_PAY": "28344.00000", "GENERAL_BUDGET_REVENUE": "1052.00000", "RESIDENT_SAVINGS": "11258.00000", "PRIMARY_SCHOOL_STUDENTS": "0.86690", "POPULATION": "7.00", "FINANCE_RMB_LOAN_BALANCE": "9726.00000", "MIDDLE_SCHOOL_STUDENTS": "0.44860", "TELEPHONE_USERS": "0.57000", "ADMINISTRATION_AREA": "6650.00000", "ABOVE_INDUSTRY_CORP": "1", "ABOVE_INDUSTRY_CORP_VALUE": "61.00000", "TOWNSHIP": "6", "VILLAGERS_COMMITTEE": "75", "TOTAL_HOMES": "19036", "RURAL_HOMES": "1.01680", "RURAL_POPULATION": "6.00", "PRACTITIONERS": "5680", "RURAL_PRACTITIONERS": "2.46610", "AGRICULTURAL_MACHINERY": "8", "FIRST_ADD_VALUE": "35521.00000", "TWO_ADD_VALUE": "9186.00000", "FOOD_YIELD": "19138.00000", "OIL_YIELD": "21172.00000", "MEAT_YIELD": "10997.00000", "BUILD_INVEST_QUOTA": "6687.00000", "SOCIAL_WELFARE_INSTITUTE": "2", "SOCIAL_WELFARE_INSTITUTE_BED": "40", "FIRST_INDUSTRY_PERSONNEL": "2.1956"}, "632621": {"ADMINISTRATIVE_CODE": "632621", "PROVINCE": "\u9752\u6d77\u7701", "CITY": "\u679c\u6d1b\u85cf\u65cf\u81ea\u6cbb\u5dde", "COUNTY": "\u739b\u6c81\u53bf", "STATISTICAL_YEAR": "2008", "HOSPITAL_BEDS": "65.00000", "BUDGET_PAY": "47044.00000", "GENERAL_BUDGET_REVENUE": "3081.00000", "RESIDENT_SAVINGS": "29150.00000", "PRIMARY_SCHOOL_STUDENTS": "0.54320", "POPULATION": "4.00", "FINANCE_RMB_LOAN_BALANCE": "23415.00000", "MIDDLE_SCHOOL_STUDENTS": "0.22570", "TELEPHONE_USERS": "0.94810", "ADMINISTRATION_AREA": "13307.00000", "ABOVE_INDUSTRY_CORP": "4", "ABOVE_INDUSTRY_CORP_VALUE": "57755.00000", "TOWNSHIP": "8", "VILLAGERS_COMMITTEE": "35", "TOTAL_HOMES": "13833", "RURAL_HOMES": "0.63890", "RURAL_POPULATION": "3.00", "PRACTITIONERS": "6197", "RURAL_PRACTITIONERS": "1.24690", "AGRICULTURAL_MACHINERY": "1", "FIRST_ADD_VALUE": "12433.00000", "TWO_ADD_VALUE": "23223.00000", "FOOD_YIELD": "108.00000", "OIL_YIELD": "178.00000", "MEAT_YIELD": "5639.00000", "BUILD_INVEST_QUOTA": "20874.00000", "SOCIAL_WELFARE_INSTITUTE": "3", "SOCIAL_WELFARE_INSTITUTE_BED": "128", "FIRST_INDUSTRY_PERSONNEL": "1.1935"}, "632622": {"ADMINISTRATIVE_CODE": "632622", "PROVINCE": "\u9752\u6d77\u7701", "CITY": "\u679c\u6d1b\u85cf\u65cf\u81ea\u6cbb\u5dde", "COUNTY": "\u73ed\u739b\u53bf", "STATISTICAL_YEAR": "2008", "HOSPITAL_BEDS": "58.00000", "BUDGET_PAY": "15987.00000", "GENERAL_BUDGET_REVENUE": "310.00000", "RESIDENT_SAVINGS": "5680.00000", "PRIMARY_SCHOOL_STUDENTS": "0.28570", "POPULATION": "3.00", "FINANCE_RMB_LOAN_BALANCE": "21.00000", "MIDDLE_SCHOOL_STUDENTS": "0.07380", "TELEPHONE_USERS": "0.21100", "ADMINISTRATION_AREA": "6139.00000", "ABOVE_INDUSTRY_CORP": "2", "ABOVE_INDUSTRY_CORP_VALUE": "235.00000", "TOWNSHIP": "9", "VILLAGERS_COMMITTEE": "32", "TOTAL_HOMES": "6747", "RURAL_HOMES": "0.48910", "RURAL_POPULATION": "2.00", "PRACTITIONERS": "1132", "RURAL_PRACTITIONERS": "0.92310", "AGRICULTURAL_MACHINERY": "1", "FIRST_ADD_VALUE": "6227.00000", "TWO_ADD_VALUE": "2321.00000", "FOOD_YIELD": "1319.00000", "OIL_YIELD": "96.00000", "MEAT_YIELD": "5150.00000", "BUILD_INVEST_QUOTA": "11088.00000", "SOCIAL_WELFARE_INSTITUTE": "7", "SOCIAL_WELFARE_INSTITUTE_BED": "66", "FIRST_INDUSTRY_PERSONNEL": "0.8818"}, "632623": {"ADMINISTRATIVE_CODE": "632623", "PROVINCE": "\u9752\u6d77\u7701", "CITY": "\u679c\u6d1b\u85cf\u65cf\u81ea\u6cbb\u5dde", "COUNTY": "\u7518\u5fb7\u53bf", "STATISTICAL_YEAR": "2008", "HOSPITAL_BEDS": "96.00000", "BUDGET_PAY": "13874.00000", "GENERAL_BUDGET_REVENUE": "215.00000", "RESIDENT_SAVINGS": "4209.00000", "PRIMARY_SCHOOL_STUDENTS": "0.33800", "POPULATION": "3.00", "FINANCE_RMB_LOAN_BALANCE": "1621.00000", "MIDDLE_SCHOOL_STUDENTS": "0.11960", "TELEPHONE_USERS": "0.15470", "ADMINISTRATION_AREA": "7046.00000", "ABOVE_INDUSTRY_CORP": "1", "ABOVE_INDUSTRY_CORP_VALUE": "755.00000", "TOWNSHIP": "7", "VILLAGERS_COMMITTEE": "36", "TOTAL_HOMES": "7066", "RURAL_HOMES": "0.61320", "RURAL_POPULATION": "3.00", "PRACTITIONERS": "1122", "RURAL_PRACTITIONERS": "1.23650", "FIRST_ADD_VALUE": "5030.00000", "TWO_ADD_VALUE": "2178.00000", "MEAT_YIELD": "3923.00000", "BUILD_INVEST_QUOTA": "9615.00000", "SOCIAL_WELFARE_INSTITUTE": "9", "SOCIAL_WELFARE_INSTITUTE_BED": "384", "FIRST_INDUSTRY_PERSONNEL": "1.1898"}, "632624": {"ADMINISTRATIVE_CODE": "632624", "PROVINCE": "\u9752\u6d77\u7701", "CITY": "\u679c\u6d1b\u85cf\u65cf\u81ea\u6cbb\u5dde", "COUNTY": "\u8fbe\u65e5\u53bf", "STATISTICAL_YEAR": "2008", "HOSPITAL_BEDS": "30.00000", "BUDGET_PAY": "17372.00000", "GENERAL_BUDGET_REVENUE": "167.00000", "RESIDENT_SAVINGS": "5434.00000", "PRIMARY_SCHOOL_STUDENTS": "0.36290", "POPULATION": "3.00", "FINANCE_RMB_LOAN_BALANCE": "2803.00000", "MIDDLE_SCHOOL_STUDENTS": "0.08360", "TELEPHONE_USERS": "0.27390", "ADMINISTRATION_AREA": "14630.00000", "ABOVE_INDUSTRY_CORP": "1", "ABOVE_INDUSTRY_CORP_VALUE": "31.00000", "TOWNSHIP": "10", "VILLAGERS_COMMITTEE": "33", "TOTAL_HOMES": "9350", "RURAL_HOMES": "0.56220", "RURAL_POPULATION": "2.00", "PRACTITIONERS": "1133", "RURAL_PRACTITIONERS": "0.99200", "FIRST_ADD_VALUE": "4588.00000", "TWO_ADD_VALUE": "3194.00000", "MEAT_YIELD": "1445.00000", "BUILD_INVEST_QUOTA": "14025.00000", "SOCIAL_WELFARE_INSTITUTE": "13", "SOCIAL_WELFARE_INSTITUTE_BED": "228", "FIRST_INDUSTRY_PERSONNEL": "0.9668"}, "632625": {"ADMINISTRATIVE_CODE": "632625", "PROVINCE": "\u9752\u6d77\u7701", "CITY": "\u679c\u6d1b\u85cf\u65cf\u81ea\u6cbb\u5dde", "COUNTY": "\u4e45\u6cbb\u53bf", "STATISTICAL_YEAR": "2008", "HOSPITAL_BEDS": "85.00000", "BUDGET_PAY": "13224.00000", "GENERAL_BUDGET_REVENUE": "192.00000", "RESIDENT_SAVINGS": "5416.00000", "PRIMARY_SCHOOL_STUDENTS": "0.32590", "POPULATION": "2.00", "MIDDLE_SCHOOL_STUDENTS": "0.04850", "TELEPHONE_USERS": "0.17400", "ADMINISTRATION_AREA": "8708.00000", "ABOVE_INDUSTRY_CORP": "2", "ABOVE_INDUSTRY_CORP_VALUE": "77.00000", "TOWNSHIP": "6", "VILLAGERS_COMMITTEE": "22", "TOTAL_HOMES": "4992", "RURAL_HOMES": "0.43560", "RURAL_POPULATION": "2.00", "PRACTITIONERS": "1161", "RURAL_PRACTITIONERS": "0.78850", "FIRST_ADD_VALUE": "6001.00000", "TWO_ADD_VALUE": "2315.00000", "MEAT_YIELD": "4376.00000", "BUILD_INVEST_QUOTA": "10743.00000", "SOCIAL_WELFARE_INSTITUTE": "7", "SOCIAL_WELFARE_INSTITUTE_BED": "116", "FIRST_INDUSTRY_PERSONNEL": "0.7508"}, "632626": {"ADMINISTRATIVE_CODE": "632626", "PROVINCE": "\u9752\u6d77\u7701", "CITY": "\u679c\u6d1b\u85cf\u65cf\u81ea\u6cbb\u5dde", "COUNTY": "\u739b\u591a\u53bf", "STATISTICAL_YEAR": "2008", "HOSPITAL_BEDS": "46.00000", "BUDGET_PAY": "12896.00000", "GENERAL_BUDGET_REVENUE": "176.00000", "RESIDENT_SAVINGS": "2093.00000", "PRIMARY_SCHOOL_STUDENTS": "0.16630", "POPULATION": "1.00", "FINANCE_RMB_LOAN_BALANCE": "1001.00000", "MIDDLE_SCHOOL_STUDENTS": "0.07260", "TELEPHONE_USERS": "0.14390", "ADMINISTRATION_AREA": "26541.00000", "ABOVE_INDUSTRY_CORP": "3", "ABOVE_INDUSTRY_CORP_VALUE": "52.00000", "TOWNSHIP": "4", "VILLAGERS_COMMITTEE": "30", "TOTAL_HOMES": "3907", "RURAL_HOMES": "0.32850", "RURAL_POPULATION": "1.00", "PRACTITIONERS": "1127", "RURAL_PRACTITIONERS": "0.58010", "FIRST_ADD_VALUE": "3537.00000", "TWO_ADD_VALUE": "1761.00000", "MEAT_YIELD": "1396.00000", "BUILD_INVEST_QUOTA": "8623.00000", "FIRST_INDUSTRY_PERSONNEL": "0.5801"}, "632701": {"ADMINISTRATIVE_CODE": "632701", "PROVINCE": "\u9752\u6d77\u7701", "CITY": "\u7389\u6811\u85cf\u65cf\u81ea\u6cbb\u5dde", "COUNTY": "\u7389\u6811\u5e02", "STATISTICAL_YEAR": "2008", "HOSPITAL_BEDS": "71.00000", "BUDGET_PAY": "29217.00000", "GENERAL_BUDGET_REVENUE": "2117.00000", "RESIDENT_SAVINGS": "31200.00000", "PRIMARY_SCHOOL_STUDENTS": "1.67360", "POPULATION": "9.00", "FINANCE_RMB_LOAN_BALANCE": "20230.00000", "MIDDLE_SCHOOL_STUDENTS": "0.48290", "TELEPHONE_USERS": "0.55000", "ADMINISTRATION_AREA": "17596.00000", "TOWNSHIP": "9", "VILLAGERS_COMMITTEE": "62", "TOTAL_HOMES": "29479", "RURAL_HOMES": "1.70870", "RURAL_POPULATION": "7.00", "PRACTITIONERS": "7024", "RURAL_PRACTITIONERS": "3.67410", "AGRICULTURAL_MACHINERY": "2", "FIRST_ADD_VALUE": "30149.00000", "TWO_ADD_VALUE": "6600.00000", "FOOD_YIELD": "4813.00000", "OIL_YIELD": "46.00000", "MEAT_YIELD": "5860.00000", "BUILD_INVEST_QUOTA": "41268.00000", "SOCIAL_WELFARE_INSTITUTE": "1", "SOCIAL_WELFARE_INSTITUTE_BED": "28", "FIRST_INDUSTRY_PERSONNEL": "3.5418"}, "632722": {"ADMINISTRATIVE_CODE": "632722", "PROVINCE": "\u9752\u6d77\u7701", "CITY": "\u7389\u6811\u85cf\u65cf\u81ea\u6cbb\u5dde", "COUNTY": "\u6742\u591a\u53bf", "STATISTICAL_YEAR": "2008", "HOSPITAL_BEDS": "65.00000", "BUDGET_PAY": "17487.00000", "GENERAL_BUDGET_REVENUE": "667.00000", "RESIDENT_SAVINGS": "300.00000", "PRIMARY_SCHOOL_STUDENTS": "0.66560", "POPULATION": "5.00", "FINANCE_RMB_LOAN_BALANCE": "19312.00000", "MIDDLE_SCHOOL_STUDENTS": "0.12900", "TELEPHONE_USERS": "0.22850", "ADMINISTRATION_AREA": "34171.00000", "ABOVE_INDUSTRY_CORP": "1", "ABOVE_INDUSTRY_CORP_VALUE": "1602.00000", "TOWNSHIP": "8", "VILLAGERS_COMMITTEE": "31", "TOTAL_HOMES": "11943", "RURAL_HOMES": "0.95480", "RURAL_POPULATION": "5.00", "PRACTITIONERS": "1455", "RURAL_PRACTITIONERS": "2.27660", "AGRICULTURAL_MACHINERY": "0", "FIRST_ADD_VALUE": "48537.00000", "TWO_ADD_VALUE": "2334.00000", "MEAT_YIELD": "3733.00000", "BUILD_INVEST_QUOTA": "16890.00000", "SOCIAL_WELFARE_INSTITUTE": "8", "SOCIAL_WELFARE_INSTITUTE_BED": "107", "FIRST_INDUSTRY_PERSONNEL": "2.2284"}, "632723": {"ADMINISTRATIVE_CODE": "632723", "PROVINCE": "\u9752\u6d77\u7701", "CITY": "\u7389\u6811\u85cf\u65cf\u81ea\u6cbb\u5dde", "COUNTY": "\u79f0\u591a\u53bf", "STATISTICAL_YEAR": "2008", "HOSPITAL_BEDS": "65.00000", "BUDGET_PAY": "22938.00000", "GENERAL_BUDGET_REVENUE": "380.00000", "RESIDENT_SAVINGS": "2466.00000", "PRIMARY_SCHOOL_STUDENTS": "0.69300", "POPULATION": "6.00", "FINANCE_RMB_LOAN_BALANCE": "2376.00000", "MIDDLE_SCHOOL_STUDENTS": "0.27930", "TELEPHONE_USERS": "0.12000", "ADMINISTRATION_AREA": "14744.00000", "ABOVE_INDUSTRY_CORP": "4", "ABOVE_INDUSTRY_CORP_VALUE": "478.00000", "TOWNSHIP": "7", "VILLAGERS_COMMITTEE": "57", "TOTAL_HOMES": "14923", "RURAL_HOMES": "1.27290", "RURAL_POPULATION": "5.00", "PRACTITIONERS": "1840", "RURAL_PRACTITIONERS": "2.39830", "AGRICULTURAL_MACHINERY": "2", "FIRST_ADD_VALUE": "15414.00000", "TWO_ADD_VALUE": "5824.00000", "FOOD_YIELD": "3571.00000", "OIL_YIELD": "55.00000", "MEAT_YIELD": "3661.00000", "BUILD_INVEST_QUOTA": "27735.00000", "SOCIAL_WELFARE_INSTITUTE": "4", "SOCIAL_WELFARE_INSTITUTE_BED": "199", "FIRST_INDUSTRY_PERSONNEL": "2.3170"}, "632724": {"ADMINISTRATIVE_CODE": "632724", "PROVINCE": "\u9752\u6d77\u7701", "CITY": "\u7389\u6811\u85cf\u65cf\u81ea\u6cbb\u5dde", "COUNTY": "\u6cbb\u591a\u53bf", "STATISTICAL_YEAR": "2008", "HOSPITAL_BEDS": "89.00000", "BUDGET_PAY": "16195.00000", "GENERAL_BUDGET_REVENUE": "270.00000", "RESIDENT_SAVINGS": "1668.00000", "PRIMARY_SCHOOL_STUDENTS": "0.43090", "POPULATION": "3.00", "FINANCE_RMB_LOAN_BALANCE": "7080.00000", "MIDDLE_SCHOOL_STUDENTS": "0.03960", "TELEPHONE_USERS": "0.28160", "ADMINISTRATION_AREA": "80040.00000", "ABOVE_INDUSTRY_CORP": "2", "ABOVE_INDUSTRY_CORP_VALUE": "338.00000", "TOWNSHIP": "6", "VILLAGERS_COMMITTEE": "20", "TOTAL_HOMES": "8556", "RURAL_HOMES": "0.66380", "RURAL_POPULATION": "3.00", "PRACTITIONERS": "1475", "RURAL_PRACTITIONERS": "1.27120", "AGRICULTURAL_MACHINERY": "0", "FIRST_ADD_VALUE": "24645.00000", "TWO_ADD_VALUE": "1436.00000", "MEAT_YIELD": "6079.00000", "BUILD_INVEST_QUOTA": "10988.00000", "SOCIAL_WELFARE_INSTITUTE": "3", "SOCIAL_WELFARE_INSTITUTE_BED": "161", "FIRST_INDUSTRY_PERSONNEL": "1.2689"}, "632725": {"ADMINISTRATIVE_CODE": "632725", "PROVINCE": "\u9752\u6d77\u7701", "CITY": "\u7389\u6811\u85cf\u65cf\u81ea\u6cbb\u5dde", "COUNTY": "\u56ca\u8c26\u53bf", "STATISTICAL_YEAR": "2008", "HOSPITAL_BEDS": "93.00000", "BUDGET_PAY": "25070.00000", "GENERAL_BUDGET_REVENUE": "410.00000", "RESIDENT_SAVINGS": "10400.00000", "PRIMARY_SCHOOL_STUDENTS": "0.94180", "POPULATION": "8.00", "FINANCE_RMB_LOAN_BALANCE": "52000.00000", "MIDDLE_SCHOOL_STUDENTS": "0.08700", "TELEPHONE_USERS": "0.20000", "ADMINISTRATION_AREA": "12695.00000", "ABOVE_INDUSTRY_CORP": "4", "ABOVE_INDUSTRY_CORP_VALUE": "1950.00000", "TOWNSHIP": "10", "VILLAGERS_COMMITTEE": "69", "TOTAL_HOMES": "17785", "RURAL_HOMES": "1.60810", "RURAL_POPULATION": "8.00", "PRACTITIONERS": "1546", "RURAL_PRACTITIONERS": "3.14880", "AGRICULTURAL_MACHINERY": "2", "FIRST_ADD_VALUE": "26288.00000", "TWO_ADD_VALUE": "3175.00000", "FOOD_YIELD": "10016.00000", "OIL_YIELD": "154.00000", "MEAT_YIELD": "5195.00000", "BUILD_INVEST_QUOTA": "19861.00000", "SOCIAL_WELFARE_INSTITUTE": "8", "FIRST_INDUSTRY_PERSONNEL": "3.1198"}, "632726": {"ADMINISTRATIVE_CODE": "632726", "PROVINCE": "\u9752\u6d77\u7701", "CITY": "\u7389\u6811\u85cf\u65cf\u81ea\u6cbb\u5dde", "COUNTY": "\u66f2\u9ebb\u83b1\u53bf", "STATISTICAL_YEAR": "2008", "HOSPITAL_BEDS": "84.00000", "BUDGET_PAY": "11813.00000", "GENERAL_BUDGET_REVENUE": "299.00000", "RESIDENT_SAVINGS": "3859.00000", "PRIMARY_SCHOOL_STUDENTS": "0.41370", "POPULATION": "3.00", "FINANCE_RMB_LOAN_BALANCE": "30382.00000", "MIDDLE_SCHOOL_STUDENTS": "0.04680", "TELEPHONE_USERS": "0.14320", "ADMINISTRATION_AREA": "47516.00000", "ABOVE_INDUSTRY_CORP": "2", "ABOVE_INDUSTRY_CORP_VALUE": "77.00000", "TOWNSHIP": "6", "VILLAGERS_COMMITTEE": "19", "TOTAL_HOMES": "8641", "RURAL_HOMES": "0.63210", "RURAL_POPULATION": "3.00", "PRACTITIONERS": "1306", "RURAL_PRACTITIONERS": "1.16740", "AGRICULTURAL_MACHINERY": "0", "FIRST_ADD_VALUE": "19267.00000", "TWO_ADD_VALUE": "4312.00000", "MEAT_YIELD": "4481.00000", "BUILD_INVEST_QUOTA": "17964.00000", "SOCIAL_WELFARE_INSTITUTE": "3", "SOCIAL_WELFARE_INSTITUTE_BED": "93", "FIRST_INDUSTRY_PERSONNEL": "0.9952"}, "632801": {"ADMINISTRATIVE_CODE": "632801", "PROVINCE": "\u9752\u6d77\u7701", "CITY": "\u6d77\u897f\u8499\u53e4\u65cf\u85cf\u65cf\u81ea\u6cbb\u5dde", "COUNTY": "\u683c\u5c14\u6728\u5e02", "STATISTICAL_YEAR": "2008", "HOSPITAL_BEDS": "490.00000", "BUDGET_PAY": "103335.00000", "GENERAL_BUDGET_REVENUE": "68439.00000", "RESIDENT_SAVINGS": "457808.00000", "PRIMARY_SCHOOL_STUDENTS": "2.07510", "POPULATION": "21.00", "FINANCE_RMB_LOAN_BALANCE": "733801.00000", "MIDDLE_SCHOOL_STUDENTS": "1.02900", "TELEPHONE_USERS": "7.08210", "ADMINISTRATION_AREA": "118954.00000", "ABOVE_INDUSTRY_CORP": "48", "ABOVE_INDUSTRY_CORP_VALUE": "1141973.00000", "TOWNSHIP": "4", "VILLAGERS_COMMITTEE": "42", "TOTAL_HOMES": "45646", "RURAL_HOMES": "0.35500", "RURAL_POPULATION": "1.00", "PRACTITIONERS": "22934", "RURAL_PRACTITIONERS": "0.90880", "AGRICULTURAL_MACHINERY": "10", "FIRST_ADD_VALUE": "9133.00000", "TWO_ADD_VALUE": "1085946.00000", "FOOD_YIELD": "8066.00000", "OIL_YIELD": "1074.00000", "MEAT_YIELD": "3261.00000", "BUILD_INVEST_QUOTA": "385571.00000", "SOCIAL_WELFARE_INSTITUTE": "2", "SOCIAL_WELFARE_INSTITUTE_BED": "24", "FIRST_INDUSTRY_PERSONNEL": "0.6691"}, "632802": {"ADMINISTRATIVE_CODE": "632802", "PROVINCE": "\u9752\u6d77\u7701", "CITY": "\u6d77\u897f\u8499\u53e4\u65cf\u85cf\u65cf\u81ea\u6cbb\u5dde", "COUNTY": "\u5fb7\u4ee4\u54c8\u5e02", "STATISTICAL_YEAR": "2008", "HOSPITAL_BEDS": "224.00000", "BUDGET_PAY": "52291.00000", "GENERAL_BUDGET_REVENUE": "8780.00000", "RESIDENT_SAVINGS": "110878.00000", "PRIMARY_SCHOOL_STUDENTS": "0.70170", "POPULATION": "7.00", "FINANCE_RMB_LOAN_BALANCE": "276678.00000", "MIDDLE_SCHOOL_STUDENTS": "0.46080", "TELEPHONE_USERS": "2.65820", "ADMINISTRATION_AREA": "27358.00000", "ABOVE_INDUSTRY_CORP": "10", "ABOVE_INDUSTRY_CORP_VALUE": "173887.00000", "TOWNSHIP": "4", "VILLAGERS_COMMITTEE": "51", "TOTAL_HOMES": "24480", "RURAL_HOMES": "0.78070", "RURAL_POPULATION": "3.00", "PRACTITIONERS": "10342", "RURAL_PRACTITIONERS": "1.73690", "AGRICULTURAL_MACHINERY": "7", "FIRST_ADD_VALUE": "11834.00000", "TWO_ADD_VALUE": "108020.00000", "FOOD_YIELD": "18236.00000", "OIL_YIELD": "3688.00000", "MEAT_YIELD": "2605.00000", "BUILD_INVEST_QUOTA": "160414.00000", "SOCIAL_WELFARE_INSTITUTE": "1", "SOCIAL_WELFARE_INSTITUTE_BED": "72", "FIRST_INDUSTRY_PERSONNEL": "1.3515"}, "632821": {"ADMINISTRATIVE_CODE": "632821", "PROVINCE": "\u9752\u6d77\u7701", "CITY": "\u6d77\u897f\u8499\u53e4\u65cf\u85cf\u65cf\u81ea\u6cbb\u5dde", "COUNTY": "\u4e4c\u5170\u53bf", "STATISTICAL_YEAR": "2008", "HOSPITAL_BEDS": "133.00000", "BUDGET_PAY": "29424.00000", "GENERAL_BUDGET_REVENUE": "3924.00000", "RESIDENT_SAVINGS": "27545.00000", "PRIMARY_SCHOOL_STUDENTS": "0.34200", "POPULATION": "4.00", "FINANCE_RMB_LOAN_BALANCE": "40391.00000", "MIDDLE_SCHOOL_STUDENTS": "0.23080", "TELEPHONE_USERS": "0.66150", "ADMINISTRATION_AREA": "12971.00000", "ABOVE_INDUSTRY_CORP": "6", "ABOVE_INDUSTRY_CORP_VALUE": "150158.00000", "TOWNSHIP": "4", "VILLAGERS_COMMITTEE": "38", "TOTAL_HOMES": "12615", "RURAL_HOMES": "0.54000", "RURAL_POPULATION": "2.00", "PRACTITIONERS": "3842", "RURAL_PRACTITIONERS": "1.44040", "AGRICULTURAL_MACHINERY": "5", "FIRST_ADD_VALUE": "11097.00000", "TWO_ADD_VALUE": "60595.00000", "FOOD_YIELD": "8030.00000", "OIL_YIELD": "2815.00000", "MEAT_YIELD": "3786.00000", "BUILD_INVEST_QUOTA": "38947.00000", "SOCIAL_WELFARE_INSTITUTE": "1", "SOCIAL_WELFARE_INSTITUTE_BED": "41", "FIRST_INDUSTRY_PERSONNEL": "1.0357"}, "632822": {"ADMINISTRATIVE_CODE": "632822", "PROVINCE": "\u9752\u6d77\u7701", "CITY": "\u6d77\u897f\u8499\u53e4\u65cf\u85cf\u65cf\u81ea\u6cbb\u5dde", "COUNTY": "\u90fd\u5170\u53bf", "STATISTICAL_YEAR": "2008", "HOSPITAL_BEDS": "119.00000", "BUDGET_PAY": "33601.00000", "GENERAL_BUDGET_REVENUE": "3609.00000", "RESIDENT_SAVINGS": "35109.00000", "PRIMARY_SCHOOL_STUDENTS": "0.72830", "POPULATION": "7.00", "FINANCE_RMB_LOAN_BALANCE": "20489.00000", "MIDDLE_SCHOOL_STUDENTS": "0.41160", "TELEPHONE_USERS": "1.22540", "ADMINISTRATION_AREA": "1465.00000", "ABOVE_INDUSTRY_CORP": "14", "ABOVE_INDUSTRY_CORP_VALUE": "44335.00000", "TOWNSHIP": "8", "VILLAGERS_COMMITTEE": "107", "TOTAL_HOMES": "21934", "RURAL_HOMES": "1.34430", "RURAL_POPULATION": "6.00", "PRACTITIONERS": "4116", "RURAL_PRACTITIONERS": "2.94240", "AGRICULTURAL_MACHINERY": "12", "FIRST_ADD_VALUE": "21413.00000", "TWO_ADD_VALUE": "29400.00000", "FOOD_YIELD": "44207.00000", "OIL_YIELD": "10675.00000", "MEAT_YIELD": "4472.00000", "BUILD_INVEST_QUOTA": "26429.00000", "SOCIAL_WELFARE_INSTITUTE": "1", "SOCIAL_WELFARE_INSTITUTE_BED": "2", "FIRST_INDUSTRY_PERSONNEL": "2.6958"}, "632823": {"ADMINISTRATIVE_CODE": "632823", "PROVINCE": "\u9752\u6d77\u7701", "CITY": "\u6d77\u897f\u8499\u53e4\u65cf\u85cf\u65cf\u81ea\u6cbb\u5dde", "COUNTY": "\u5929\u5cfb\u53bf", "STATISTICAL_YEAR": "2008", "HOSPITAL_BEDS": "94.00000", "BUDGET_PAY": "28573.00000", "GENERAL_BUDGET_REVENUE": "12205.00000", "PRIMARY_SCHOOL_STUDENTS": "0.27070", "POPULATION": "2.00", "FINANCE_RMB_LOAN_BALANCE": "25258.00000", "MIDDLE_SCHOOL_STUDENTS": "0.12500", "TELEPHONE_USERS": "0.30000", "ADMINISTRATION_AREA": "25000.00000", "ABOVE_INDUSTRY_CORP": "3", "ABOVE_INDUSTRY_CORP_VALUE": "303550.00000", "TOWNSHIP": "10", "VILLAGERS_COMMITTEE": "62", "TOTAL_HOMES": "6125", "RURAL_HOMES": "0.30740", "RURAL_POPULATION": "2.00", "PRACTITIONERS": "2130", "RURAL_PRACTITIONERS": "0.78600", "AGRICULTURAL_MACHINERY": "1", "FIRST_ADD_VALUE": "15609.00000", "TWO_ADD_VALUE": "139333.00000", "MEAT_YIELD": "6530.00000", "BUILD_INVEST_QUOTA": "34649.00000", "SOCIAL_WELFARE_INSTITUTE": "17", "SOCIAL_WELFARE_INSTITUTE_BED": "21", "FIRST_INDUSTRY_PERSONNEL": "0.7610"}}